Workbook
Name _splatka: 'prijem - EUR'!$F$126
Name bridge_YN: [1]CALC!$K$18
Name doba_m: 'prijem - EUR'!$F$50
Name doba_m_z: 'prijem -inna mena'!$F$55
Name hladaj: 'prijem - EUR'!$D$126
Name hladaj_ks: 'prijem - EUR'!$D$127
Name ks_splatka: 'prijem - EUR'!$F$127
Name LCI: 'prijem - EUR'!#REF!
Name LCI_z: 'prijem -inna mena'!#REF!
Name ltv: 'prijem - EUR'!#REF!
Name ltv_high: 'prijem - EUR'!$F$70
Name ltv_high_z: 'prijem -inna mena'!$F$61
Name ltv_low: 'prijem - EUR'!#REF!
Name poplatok_t0: 'prijem - EUR'!$F$85
Name pv_splatok: 'prijem - EUR'!$E$126
Name pv_splatok_ks: 'prijem - EUR'!$E$127
Name rpmn: 'prijem - EUR'!$F$93
Name rpmn_ks: 'prijem - EUR'!$F$94
Name rpmn_ks_z: 'prijem -inna mena'!$F$96
Name rpmn_z: 'prijem -inna mena'!$F$95
Name splatka: 'prijem - EUR'!$F$84
Name splatka_ks: 'prijem - EUR'!$F$89
Name splatka_ks_z: 'prijem -inna mena'!$F$92
Name splatka_z: 'prijem -inna mena'!$F$89
Name urokova_sadzba: 'prijem - EUR'!$F$73
Name urokova_sadzba_z: 'prijem -inna mena'!$F$78
Name vyska_uveru: 'prijem - EUR'!$F$48
Name vyska_uveru_LI: 'prijem - EUR'!$F$49
Name vyska_uveru_LI_z: 'prijem -inna mena'!$F$54
Name vyska_uveru_z: 'prijem -inna mena'!$F$53
Name zabezpecenie: 'prijem - EUR'!$F$51
Name zabezpecenie_z: 'prijem -inna mena'!$F$56

Sheet Úrokový lístok

Sheet prijem - EUR
C1: Kalkulačka mHypotéka
D3: Dátum zadania do systému | F3: 45860
F4: =IF(ISBLANK(F3),"DÁTUM PODANIA!","OK") -> OK
D5: Číslo žiadosti
D7: Mesačný čistý príjem domácnosti v EUR | F7: =MAX(F8+F11+F14+F17-F9-F12-F15-F18,0) -> 0 | I7: Minimální věk
D8: Čistý príjem žiadateľa č.1 | F8: 0 | I8: =IF(F20=4,MIN(F22,F24,F26,F28),IF(F20=3,MIN(F22,F24,F26),IF(F20=2,MIN(F22,F24),F22))) -> 0
D9: z toho príjem z výživného a sirotského dôchodku | F9: 0
D10: Náklady bývanie žiadateľa č.1 | F10: 0
D11: Čistý príjem žiadateľa č.2 | F11: 0
D12: z toho príjem z výživného a sirotského dôchodku | F12: 0
D13: Náklady bývanie žiadateľa č.2 | F13: 0
D14: Čistý príjem žiadateľa č.3 | F14: 0
D15: z toho príjem z výživného a sirotského dôchodku | F15: 0
D16: Náklady bývanie žiadateľa č.3 | F16: 0
D17: Čistý príjem žiadateľa č.4 | F17: 0
D18: z toho príjem z výživného a sirotského dôchodku | F18: 0
D19: Náklady bývanie žiadateľa č.4 | F19: 0
D20: Počet žiadatelov | F20: 1
D21: Dátum narodenia žiadateľa č. 1 | I21: =IF(F22<41,8,IF(F22+doba_m/12<65,8,MAX(8-0.25*(F22-40),3))) -> 8
D22: Vek žiadateľa č.1 na limity | F22: =IF(F21="",0,IF(AND(DAY(F3)=DAY(F21),MONTH(F3)=MONTH(F21)),YEAR(F3)-YEAR(F21),FLOOR(YEARFRAC(F21,F3,1),1))) -> 0
D23: Dátum narodenia žiadateľa č. 2 | I23: =IF(F24<41,8,IF(F24+doba_m/12<65,8,MAX(8-0.25*(F24-40),3))) -> 8
D24: Vek žiadateľa č.2 na limity | F24: =IF(F23="",0,IF(AND(DAY(F3)=DAY(F23),MONTH(F3)=MONTH(F23)),YEAR(F3)-YEAR(F23),FLOOR(YEARFRAC(F23,F3,1),1))) -> 0
D25: Dátum narodenia žiadateľa č. 3 | I25: =IF(F26<41,8,IF(F26+doba_m/12<65,8,MAX(8-0.25*(F26-40),3))) -> 8
D26: Vek žiadateľa č.3 na limity | F26: =IF(F25="",0,IF(AND(DAY(F3)=DAY(F25),MONTH(F3)=MONTH(F25)),YEAR(F3)-YEAR(F25),FLOOR(YEARFRAC(F25,F3,1),1))) -> 0
D27: Dátum narodenia žiadateľa č. 4 | I27: =IF(F28<41,8,IF(F28+doba_m/12<65,8,MAX(8-0.25*(F28-40),3))) -> 8
D28: Vek žiadateľa č.4 na limity | F28: =IF(F27="",0,IF(AND(DAY(F3)=DAY(F27),MONTH(F3)=MONTH(F27)),YEAR(F3)-YEAR(F27),FLOOR(YEARFRAC(F27,F3,1),1))) -> 0
D29: Počet žiadatelmi vyživovaných osôb
D30: Number of dependants with applicants | F30: =$F$20+$F$29 -> 1
D31: v tom detí
D32: Available income (including household expenses) | F32: =MAX(0.95*(F7-MAX($F$34,$F$35)),0) -> 0 | I32: =MIN(MAX(0.95*(F7-MAX($F$34,$F$35)),0),F7*0.75) -> 0
D33: Expenses - according to Slovak law (COSTS) | F33: =IF($F$30=0,0,(284.13+MAX(($F$30-$F$31-1)*198.22+($F$31)*129.74-F9-F12-F15-F18,0)+$F$43)) -> 284.13
D34: Expenses - according to Slovak law (COSTS) + Housing cost | F34: =IF($F$30=0,0,($F$33+F10+F13+F16+F19)) -> 284.13
D35: Expenses - according to the Bank's model (KUGD) | F35: =IF($F$30=0,0,MAX($F$30*((185*($F$30^(-0.4)))^(1-0.4))*(($F$7/$F$30)^(0.4)),0)) -> 0
D39: Výška mesačných splátok splátkových úverov | F39: 0
D40: Limity kontokorentných úverov | F40: 0
D41: Limity kreditných kariet | F41: 0
D42: Výška mesačných splátok alimentov, exekúcií a iných záväzkov | F42: 0
D43: Prepočtená výška mesačných splátok alimentov, exekúcií a iných záväzkov | F43: =IF($F$42=0,0,IF($F$42>30,$F$42,30)) -> 0
D44: Free income (including liabilities) | F44: =MAX((MIN($F$32,0.75*F7)-$F$39-0.03*$F$40-0.03*$F$41),0) -> 0
D48: Žiadaná čiastka úveru v EUR | F48: 0
D49: Žiadaná čiastka úveru s Life Insurance | F49: =vyska_uveru+F87 -> 0
D50: Žiadaná doba splátkoveho úveru (v mesiacoch)
D51: Hodnota nehnuteľ. ponúkanej ako zabezpečenie úveru v EUR č.1 | F51: 0
D52: Volná hodnota nehnuteľnosti č.1 | F52: 0
D53: Cena ZP č. 1 | F53: 0
D54: Poistné č. 1 ročné | F54: 0
D55: Poistné č. 1 za dobu splácania | F55: =(F54/12)*doba_m -> 0
D56: Štandardná hodnota ukazovateľa LtV (% | F56: 0.8
D57: Maximálna hodnota ukazovateľa LtV (%) | F57: =IF(F56=80%,90%,IF(F56=70%,"80%",IF(C116=2,"75%","90%"))) -> 0.9
D58: Hodnota nehnuteľ. ponúkanej ako zabezpečenie úveru v EUR č.2 | F58: 0
D59: Volná hodnota nehnuteľnosti č.2
D60: Cena ZP č. 2
D61: Poistné č. 2 ročné
D62: Poistné č. 2 za celú dobu splácania | F62: =(F61/12)*doba_m -> 0
D63: Štandardná hodnota ukazovateľa LtV (%) | F63: 0.7
D64: Maximálna hodnota ukazovateľa LtV (%) | F64: =IF(F63=80%,100%,IF(F63=70%,"80%",IF(C116=2,"75%","90%"))) -> 80%
D65: Hodnota nehnuteľ. ponúkanej ako zabezpečenie úveru v EUR č.3 | F65: 0
D66: Volná hodnota nehnuteľnosti č.3
D67: Cena ZP č. 3
D68: Poistné č. 3 ročné
D69: Poistné č. 3 za celú dobu splácania | F69: =(F68/12)*doba_m -> 0
D70: Štandardná hodnota ukazovateľa LtV (%) | F70: 0.65
D71: Maximálna hodnota ukazovateľa LtV (%) | F71: =IF(F70=80%,100%,IF(F70=70%,"80%",IF(C116=2,"75%","90%"))) -> 90%
D72: Skutočná hodnota ukazovateľa LtV (%) | F72: =IFERROR(IF(ISBLANK($F$52)=TRUE,IF(ISBLANK($F$56)=TRUE,0,(F49/(F51+F58+F65))),(zabezpecenie-F52+F58-F59+F65-F66+vyska_uveru_LI)/(zabezpecenie+F58+F65)),0) -> 0
D73: Ročná úroková sadzba (%) | F73: 0
D74: Účelový/Neúčelový úver nebo Štandartná/Neštandartná neh.
D75: Příjem v CZK/Příjem v cizí měne
D81: Maximálna dostupná čiastka úveru na základe finančného profilu v EUR | F81: =IFERROR(IF(I8<60,(IF(ISBLANK($F$50)=TRUE,0,MIN(MAX($F$44/((E116/12)/(1-(1+(E116/12))^(-MIN($F$50,360)))),0),F7/(1/doba_m+F73/12))/E119)),(IF(doba_m>60,IF(ISBLANK($F$50)=TRUE,0,MIN(MAX($F$44/((E116/12)/(1-(1+(E116/12))^(-60))),0),F7/(1/doba_m+F73/12))/E119),IF(ISBLANK($F$50)=TRUE,0,MIN(MAX($F$44/((E116/12)/(1-(1+(E116/12))^(-doba_m))),0),F7/(1/doba_m+F73/12))/E119)))),0) -> 0
D82: Maximalná dostupná čiastka úveru z ohľadom na hodnotu zabezpečenia úveru a maximálnej hodnoty ukazovateľa LtV | F82: =IFERROR(MIN(IF(F7<750,IF(ISBLANK($F$50)=TRUE,"",MIN(0.9*$F$52+0.9*$F$59+0.9*$F$66,$F$81)),IF(ISBLANK($F$50)=TRUE,"",MIN($F$57*$F$52+$F$64*$F$59+$F$71*$F$66,$F$81))),($F$57*$F$52+$F$64*$F$59+$F$71*$F$66)),0) -> 0
D84: Vypočítaná anuitná splátka žiadaného úveru | F84: =IF(ISERR(ROUND(IF(ISBLANK($F$50)=TRUE,"",(IF(ISBLANK($F$73)=TRUE,"",$F$49*(($F$73/12)/(1-(1+($F$73/12))^(-$F$50)))))),2)),0,ROUND(IF(ISBLANK($F$50)=TRUE,"",(IF(ISBLANK($F$73)=TRUE,"",$F$49*(($F$73/12)/(1-(1+($F$73/12))^(-$F$50)))))),2)) -> 0
D85: Pojištění nízkého vkladu (splatné na začátku) | F85: =IF(ISBLANK(zabezpecenie)=TRUE,"",(IF((vyska_uveru/zabezpecenie)*100%>ltv,((vyska_uveru/zabezpecenie)*100%-ltv)*zabezpecenie*0.035,"0"))) -> #DIV/0!
D86: Vypočítaná anuitná splátka žiadaného úveru - DSTI | F86: =IF(ISERR(ROUND(IF(ISBLANK($F$49)=TRUE,"",(IF(ISBLANK($F$73)=TRUE,"",$F$49*((MIN(urokova_sadzba+0.02,0.06)/12)/(1-(1+(MIN(urokova_sadzba+0.02,0.06)/12))^(-360)))))),2)),0,ROUND(IF(ISBLANK($F$49)=TRUE,"",(IF(ISBLANK($F$73)=TRUE,"",$F$49*((MIN(urokova_sadzba+0.02,0.06)/12)/(1-(1+(MIN(urokova_sadzba+0.02,0.06)/12))^(-360)))))),2)) -> 0
D87: Poistenie Life Insurance zahrnuté do výšky úveru | F87: =ROUND(IF(I87,F129,0),2) -> 0 | I87: FALSE
D88: Poistenie Life Insurance nezahrnuté do výšky úveru | F88: =ROUND(IF(I88,F130,0),2) -> 0 | I88: FALSE
D89: Prvá klesajúca splátka žiadaného úveru | F89: =IF(ISERR(IF(ISBLANK($F$50)=TRUE,"",IF(ISBLANK($F$73)=TRUE,"",$F$49/$F$50+$F$49*$F$73/12))),0,IF(ISBLANK($F$50)=TRUE,"",IF(ISBLANK($F$73)=TRUE,"",$F$49/$F$50+$F$49*$F$73/12)))
D90: Prvá klesajúca splátka žiadaného úveru - DSTI | F90: =IF(ISERR(IF(ISBLANK($F$49)=TRUE,"",IF(ISBLANK($F$73)=TRUE,"",$F$49/360+$F$49*MIN(urokova_sadzba+0.02,0.06)/12))),0,IF(ISBLANK($F$49)=TRUE,"",IF(ISBLANK($F$73)=TRUE,"",$F$49/360+$F$49*MIN(urokova_sadzba+0.02,0.06)/12))) -> 0
D91: Celk. zaplatená čiastka anuitne splátky (vrátane poplatkov) | F91: =IF(ISERR(RPSN!C13),0,(RPSN!C13)) -> 0
D92: Celk. zaplatená čiastka klesajúce splátky (vrátane poplatkov) | F92: =IF(ISERR(RPSN!M13),0,(RPSN!M13)) -> 0
D93: RPMN pre anuitne splátky | F93: =IF(ISERR(RPSN!C12),0,(RPSN!C12)) -> 0
D94: RPMN pre klesajúce splátky | F94: =IF(ISERR(RPSN!M12),0,(RPSN!M12)) -> 0
E98: Zostatok splátkových úverov | F98: 0
E99: Limit revolvingových úverov | F99: =$F$40 -> 0
E100: Využitý limit revolvingových úverov | F100: 0
E101: Nevyužitý limit revolvingových úverov | F101: =$F$99-$F$100 -> 0
E102: Limit kreditných kariet | F102: =$F$41 -> 0
E103: Využitý limit kreditných kariet | F103: 0
E104: Nevyužitý limit kreditných kariet | F104: =$F$102-$F$103 -> 0
E105: Schválená výška úveru | F105: =MIN(vyska_uveru_LI,F81) -> 0
E106: DTI | F106: =($F$98+$F$100+$F$103+$F$105+0.2*($F$101+$F$104))/(12*$F$7) -> #DIV/0!
E107: DTI limit | F107: =((F8-F9)*I21+(F11-F12)*I23+(F14-F15)*I25+(F17-F18)*I27)/F7 -> #DIV/0!
E108: Vyhodnotenie DTI | F108: =IF(F106>F107,"Překročen limit DTI","OK") -> #DIV/0!
E109: DSTI (anuitné) | F109: =($F$39+0.03*$F$40+0.03*$F$41+MAX(splatka,$F$86))/($F$7-$F$33) -> 0
E110: Vyhodnotenie DSTI (anuitné) | F110: =IF(F109>=0.6,"Překročen limit DSTI","OK") -> OK
E111: DSTI (klesajúce) | F111: =($F$39+0.03*$F$40+0.03*$F$41+MAX(splatka_ks,$F$90))/($F$7-$F$33) -> 0
E112: Vyhodnotenie DSTI (klesajúce) | F112: =IF(F111>=0.6,"Překročen limit DSTI","OK") -> OK
E113: Splatnosť (anuitné) | F113: =IF($F$50<=360,"OK",IF(AND($F$72<=0.8,$F$106<=8,$F$109<=0.6),"OK","UPRAV SPLATNOST")) -> OK
E114: Splatnosť (klesajúce) | F114: =IF($F$50<=360,"OK",IF(AND($F$72<=0.8,$F$106<=8,$F$111<=0.6),"OK","UPRAV SPLATNOST")) -> OK
C116: 1 | D116: Účel/štandard | E116: =MAX(urokova_sadzba,MIN(urokova_sadzba+0.02,0.06)) -> 0.02
D117: Neúčel/štandard
D118: Účel/neštandard
...

Sheet RPSN
A2: anuita | K2: klesajuce
B3: vyska uveru | C3: ='prijem - EUR'!F49 -> 0 | L3: vyska uveru | M3: ='prijem - EUR'!F49 -> 0
B4: sadzba | C4: =urokova_sadzba -> 0 | L4: sadzba | M4: =urokova_sadzba -> 0
B5: splatnost | C5: =doba_m -> 0 | L5: splatnost | M5: =doba_m -> 0
B6: cena ZP | C6: ='prijem - EUR'!F53+'prijem - EUR'!F60+'prijem - EUR'!F67 -> 0 | L6: cena ZP | M6: ='prijem - EUR'!F53+'prijem - EUR'!F60+'prijem - EUR'!F67 -> 0
B7: poistné za rok | C7: ='prijem - EUR'!F54+'prijem - EUR'!F61+'prijem - EUR'!F68 -> 0 | L7: poistné za rok | M7: ='prijem - EUR'!F54+'prijem - EUR'!F61+'prijem - EUR'!F68 -> 0
B8: poistné za celú dobu | C8: ='prijem - EUR'!F55+'prijem - EUR'!F62+'prijem - EUR'!F69 -> 0 | L8: poistné za celú dobu | M8: ='prijem - EUR'!F55+'prijem - EUR'!F62+'prijem - EUR'!F69 -> 0
B9: vklad do katastru | C9: ='prijem - EUR'!E122+'prijem - EUR'!E123+'prijem - EUR'!E124 -> 0 | L9: vklad do katastru | M9: ='prijem - EUR'!E122+'prijem - EUR'!E123+'prijem - EUR'!E124 -> 0
B10: LCI | C10: =LCI -> #REF! | L10: LCI | M10: =LCI -> #REF!
B11: Life | C11: ='prijem - EUR'!F87 -> 0 | L11: Life | M11: ='prijem - EUR'!F87 -> 0
B12: RPSN | C12: =(1+IRR(B16:B496,1%))^12-1 -> #VALUE! | L12: RPSN | M12: =(1+IRR(L16:L496,1%))^12-1 -> #VALUE!
B13: celkova zaplatena | C13: =(SUM(B17:B496)*-1)+C6+C8+C9+H17 -> #NUM! | L13: celkova zaplatena | M13: =(SUM(L17:L496)*-1)+M6+M8+M9+R17 -> #DIV/0!
B15: CF | C15: zostatok | L15: CF | M15: zostatok
A16: mesiac | B16: =C3-C6-C7-C9-C11-H17 -> 0 | C16: =C3 -> 0 | D16: istina | E16: urok | F16: splatka | G16: splatka LI | H16: LI nezapoč | K16: mesiac | L16: =M3-M6-M7-M9-M11-R17 -> 0 | M16: =M3 -> 0 | N16: istina | O16: urok | P16: splatka | Q16: splatka LI | R16: LI nezapoč
A17: 1 | B17: =IF(C16>0.00001,F17-G17,0) -> 0 | C17: =MAX(C16-D17,0) -> #NUM! | D17: =(F17-E17)*-1 -> #NUM! | E17: =IPMT($C$4/12,1,$C$5,C16) -> #NUM! | F17: =PMT($C$4/12,$C$5,$C$3) -> #NUM! | H17: ='prijem - EUR'!F88 -> 0 | K17: 1 | L17: =IF(M16>0.00001,P17-Q17,0)*-1 -> 0 | M17: =MAX(M16-N17,0) -> #DIV/0! | N17: =$M$16/$M$5 -> #DIV/0! | O17: =M16*$M$4/12 -> 0 | P17: =O17+N17 -> #DIV/0! | R17: ='prijem - EUR'!F88 -> 0
A18: 2 | B18: =IF(C17>0.00001,F18-G18,0) -> #NUM! | C18: =MAX(C17-D18,0) -> #NUM! | D18: =(F18-E18)*-1 -> #NUM! | E18: =IPMT($C$4/12,1,$C$5,C17) -> #NUM! | F18: =PMT($C$4/12,$C$5,$C$3) -> #NUM! | K18: 2 | L18: =IF(M17>0.00001,P18-Q18,0)*-1 -> #DIV/0! | M18: =MAX(M17-N18,0) -> #DIV/0! | N18: =$M$16/$M$5 -> #DIV/0! | O18: =M17*$M$4/12 -> #DIV/0! | P18: =O18+N18 -> #DIV/0!
A19: 3 | B19: =IF(C18>0.00001,F19-G19,0) -> #NUM! | C19: =MAX(C18-D19,0) -> #NUM! | D19: =(F19-E19)*-1 -> #NUM! | E19: =IPMT($C$4/12,1,$C$5,C18) -> #NUM! | F19: =PMT($C$4/12,$C$5,$C$3) -> #NUM! | K19: 3 | L19: =IF(M18>0.00001,P19-Q19,0)*-1 -> #DIV/0! | M19: =MAX(M18-N19,0) -> #DIV/0! | N19: =$M$16/$M$5 -> #DIV/0! | O19: =M18*$M$4/12 -> #DIV/0! | P19: =O19+N19 -> #DIV/0!
A20: 4 | B20: =IF(C19>0.00001,F20-G20,0) -> #NUM! | C20: =MAX(C19-D20,0) -> #NUM! | D20: =(F20-E20)*-1 -> #NUM! | E20: =IPMT($C$4/12,1,$C$5,C19) -> #NUM! | F20: =PMT($C$4/12,$C$5,$C$3) -> #NUM! | K20: 4 | L20: =IF(M19>0.00001,P20-Q20,0)*-1 -> #DIV/0! | M20: =MAX(M19-N20,0) -> #DIV/0! | N20: =$M$16/$M$5 -> #DIV/0! | O20: =M19*$M$4/12 -> #DIV/0! | P20: =O20+N20 -> #DIV/0!
A21: 5 | B21: =IF(C20>0.00001,F21-G21,0) -> #NUM! | C21: =MAX(C20-D21,0) -> #NUM! | D21: =(F21-E21)*-1 -> #NUM! | E21: =IPMT($C$4/12,1,$C$5,C20) -> #NUM! | F21: =PMT($C$4/12,$C$5,$C$3) -> #NUM! | K21: 5 | L21: =IF(M20>0.00001,P21-Q21,0)*-1 -> #DIV/0! | M21: =MAX(M20-N21,0) -> #DIV/0! | N21: =$M$16/$M$5 -> #DIV/0! | O21: =M20*$M$4/12 -> #DIV/0! | P21: =O21+N21 -> #DIV/0!
A22: 6 | B22: =IF(C21>0.00001,F22-G22,0) -> #NUM! | C22: =MAX(C21-D22,0) -> #NUM! | D22: =(F22-E22)*-1 -> #NUM! | E22: =IPMT($C$4/12,1,$C$5,C21) -> #NUM! | F22: =PMT($C$4/12,$C$5,$C$3) -> #NUM! | K22: 6 | L22: =IF(M21>0.00001,P22-Q22,0)*-1 -> #DIV/0! | M22: =MAX(M21-N22,0) -> #DIV/0! | N22: =$M$16/$M$5 -> #DIV/0! | O22: =M21*$M$4/12 -> #DIV/0! | P22: =O22+N22 -> #DIV/0!
A23: 7 | B23: =IF(C22>0.00001,F23-G23,0) -> #NUM! | C23: =MAX(C22-D23,0) -> #NUM! | D23: =(F23-E23)*-1 -> #NUM! | E23: =IPMT($C$4/12,1,$C$5,C22) -> #NUM! | F23: =PMT($C$4/12,$C$5,$C$3) -> #NUM! | K23: 7 | L23: =IF(M22>0.00001,P23-Q23,0)*-1 -> #DIV/0! | M23: =MAX(M22-N23,0) -> #DIV/0! | N23: =$M$16/$M$5 -> #DIV/0! | O23: =M22*$M$4/12 -> #DIV/0! | P23: =O23+N23 -> #DIV/0!
A24: 8 | B24: =IF(C23>0.00001,F24-G24,0) -> #NUM! | C24: =MAX(C23-D24,0) -> #NUM! | D24: =(F24-E24)*-1 -> #NUM! | E24: =IPMT($C$4/12,1,$C$5,C23) -> #NUM! | F24: =PMT($C$4/12,$C$5,$C$3) -> #NUM! | K24: 8 | L24: =IF(M23>0.00001,P24-Q24,0)*-1 -> #DIV/0! | M24: =MAX(M23-N24,0) -> #DIV/0! | N24: =$M$16/$M$5 -> #DIV/0! | O24: =M23*$M$4/12 -> #DIV/0! | P24: =O24+N24 -> #DIV/0!
A25: 9 | B25: =IF(C24>0.00001,F25-G25,0) -> #NUM! | C25: =MAX(C24-D25,0) -> #NUM! | D25: =(F25-E25)*-1 -> #NUM! | E25: =IPMT($C$4/12,1,$C$5,C24) -> #NUM! | F25: =PMT($C$4/12,$C$5,$C$3) -> #NUM! | K25: 9 | L25: =IF(M24>0.00001,P25-Q25,0)*-1 -> #DIV/0! | M25: =MAX(M24-N25,0) -> #DIV/0! | N25: =$M$16/$M$5 -> #DIV/0! | O25: =M24*$M$4/12 -> #DIV/0! | P25: =O25+N25 -> #DIV/0!
A26: 10 | B26: =IF(C25>0.00001,F26-G26,0) -> #NUM! | C26: =MAX(C25-D26,0) -> #NUM! | D26: =(F26-E26)*-1 -> #NUM! | E26: =IPMT($C$4/12,1,$C$5,C25) -> #NUM! | F26: =PMT($C$4/12,$C$5,$C$3) -> #NUM! | K26: 10 | L26: =IF(M25>0.00001,P26-Q26,0)*-1 -> #DIV/0! | M26: =MAX(M25-N26,0) -> #DIV/0! | N26: =$M$16/$M$5 -> #DIV/0! | O26: =M25*$M$4/12 -> #DIV/0! | P26: =O26+N26 -> #DIV/0!
A27: 11 | B27: =IF(C26>0.00001,F27-G27,0) -> #NUM! | C27: =MAX(C26-D27,0) -> #NUM! | D27: =(F27-E27)*-1 -> #NUM! | E27: =IPMT($C$4/12,1,$C$5,C26) -> #NUM! | F27: =PMT($C$4/12,$C$5,$C$3) -> #NUM! | K27: 11 | L27: =IF(M26>0.00001,P27-Q27,0)*-1 -> #DIV/0! | M27: =MAX(M26-N27,0) -> #DIV/0! | N27: =$M$16/$M$5 -> #DIV/0! | O27: =M26*$M$4/12 -> #DIV/0! | P27: =O27+N27 -> #DIV/0!
A28: 12 | B28: =IF(C27>0.00001,F28-G28,0) -> #NUM! | C28: =MAX(C27-D28,0) -> #NUM! | D28: =(F28-E28)*-1 -> #NUM! | E28: =IPMT($C$4/12,1,$C$5,C27) -> #NUM! | F28: =PMT($C$4/12,$C$5,$C$3) -> #NUM! | K28: 12 | L28: =IF(M27>0.00001,P28-Q28,0)*-1 -> #DIV/0! | M28: =MAX(M27-N28,0) -> #DIV/0! | N28: =$M$16/$M$5 -> #DIV/0! | O28: =M27*$M$4/12 -> #DIV/0! | P28: =O28+N28 -> #DIV/0!
A29: 13 | B29: =IF(C28>0.00001,F29-G29,0) -> #NUM! | C29: =MAX(C28-D29,0) -> #NUM! | D29: =(F29-E29)*-1 -> #NUM! | E29: =IPMT($C$4/12,1,$C$5,C28) -> #NUM! | F29: =PMT($C$4/12,$C$5,$C$3) -> #NUM! | K29: 13 | L29: =IF(M28>0.00001,P29-Q29,0)*-1 -> #DIV/0! | M29: =MAX(M28-N29,0) -> #DIV/0! | N29: =$M$16/$M$5 -> #DIV/0! | O29: =M28*$M$4/12 -> #DIV/0! | P29: =O29+N29 -> #DIV/0!
... A40: 24 | B40: =IF(C39>0.00001,F40-G40,0) -> #NUM! | C40: =MAX(C39-D40,0) -> #NUM! | D40: =(F40-E40)*-1 -> #NUM! | E40: =IPMT($C$4/12,1,$C$5,C39) -> #NUM! | F40: =PMT($C$4/12,$C$5,$C$3) -> #NUM! | K40: 24 | L40: =IF(M39>0.00001,P40-Q40,0)*-1 -> #DIV/0! | M40: =MAX(M39-N40,0) -> #DIV/0! | N40: =$M$16/$M$5 -> #DIV/0! | O40: =M39*$M$4/12 -> #DIV/0! | P40: =O40+N40 -> #DIV/0!
A41: 25 | B41: =IF(C40>0.00001,F41-G41,0) -> #NUM! | C41: =MAX(C40-D41,0) -> #NUM! | D41: =(F41-E41)*-1 -> #NUM! | E41: =IPMT($C$4/12,1,$C$5,C40) -> #NUM! | F41: =PMT($C$4/12,$C$5,$C$3) -> #NUM! | G41: =IF('prijem - EUR'!$I$87=TRUE,IF($C$11>0,0.00025*C40,0),IF('prijem - EUR'!$I$88=TRUE,IF('prijem - EUR'!$F$88>0,0.00025*C40,0),0)) -> 0 | K41: 25 | L41: =IF(M40>0.00001,P41-Q41,0)*-1 -> #DIV/0! | M41: =MAX(M40-N41,0) -> #DIV/0! | N41: =$M$16/$M$5 -> #DIV/0! | O41: =M40*$M$4/12 -> #DIV/0! | P41: =O41+N41 -> #DIV/0! | Q41: =IF('prijem - EUR'!$I$87=TRUE,IF($C$11>0,0.00025*M40,0),IF('prijem - EUR'!$I$88=TRUE,IF('prijem - EUR'!$F$88>0,0.00025*M40*-1,0),0)) -> 0
A42: 26 | B42: =IF(C41>0.00001,F42-G42,0) -> #NUM! | C42: =MAX(C41-D42,0) -> #NUM! | D42: =(F42-E42)*-1 -> #NUM! | E42: =IPMT($C$4/12,1,$C$5,C41) -> #NUM! | F42: =PMT($C$4/12,$C$5,$C$3) -> #NUM! | G42: =IF('prijem - EUR'!$I$87=TRUE,IF($C$11>0,0.00025*C41,0),IF('prijem - EUR'!$I$88=TRUE,IF('prijem - EUR'!$F$88>0,0.00025*C41,0),0)) -> 0 | K42: 26 | L42: =IF(M41>0.00001,P42-Q42,0)*-1 -> #DIV/0! | M42: =MAX(M41-N42,0) -> #DIV/0! | N42: =$M$16/$M$5 -> #DIV/0! | O42: =M41*$M$4/12 -> #DIV/0! | P42: =O42+N42 -> #DIV/0! | Q42: =IF('prijem - EUR'!$I$87=TRUE,IF($C$11>0,0.00025*M41,0),IF('prijem - EUR'!$I$88=TRUE,IF('prijem - EUR'!$F$88>0,0.00025*M41*-1,0),0)) -> 0
A43: 27 | B43: =IF(C42>0.00001,F43-G43,0) -> #NUM! | C43: =MAX(C42-D43,0) -> #NUM! | D43: =(F43-E43)*-1 -> #NUM! | E43: =IPMT($C$4/12,1,$C$5,C42) -> #NUM! | F43: =PMT($C$4/12,$C$5,$C$3) -> #NUM! | G43: =IF('prijem - EUR'!$I$87=TRUE,IF($C$11>0,0.00025*C42,0),IF('prijem - EUR'!$I$88=TRUE,IF('prijem - EUR'!$F$88>0,0.00025*C42,0),0)) -> 0 | K43: 27 | L43: =IF(M42>0.00001,P43-Q43,0)*-1 -> #DIV/0! | M43: =MAX(M42-N43,0) -> #DIV/0! | N43: =$M$16/$M$5 -> #DIV/0! | O43: =M42*$M$4/12 -> #DIV/0! | P43: =O43+N43 -> #DIV/0! | Q43: =IF('prijem - EUR'!$I$87=TRUE,IF($C$11>0,0.00025*M42,0),IF('prijem - EUR'!$I$88=TRUE,IF('prijem - EUR'!$F$88>0,0.00025*M42*-1,0),0)) -> 0
A44: 28 | B44: =IF(C43>0.00001,F44-G44,0) -> #NUM! | C44: =MAX(C43-D44,0) -> #NUM! | D44: =(F44-E44)*-1 -> #NUM! | E44: =IPMT($C$4/12,1,$C$5,C43) -> #NUM! | F44: =PMT($C$4/12,$C$5,$C$3) -> #NUM! | G44: =IF('prijem - EUR'!$I$87=TRUE,IF($C$11>0,0.00025*C43,0),IF('prijem - EUR'!$I$88=TRUE,IF('prijem - EUR'!$F$88>0,0.00025*C43,0),0)) -> 0 | K44: 28 | L44: =IF(M43>0.00001,P44-Q44,0)*-1 -> #DIV/0! | M44: =MAX(M43-N44,0) -> #DIV/0! | N44: =$M$16/$M$5 -> #DIV/0! | O44: =M43*$M$4/12 -> #DIV/0! | P44: =O44+N44 -> #DIV/0! | Q44: =IF('prijem - EUR'!$I$87=TRUE,IF($C$11>0,0.00025*M43,0),IF('prijem - EUR'!$I$88=TRUE,IF('prijem - EUR'!$F$88>0,0.00025*M43*-1,0),0)) -> 0
A45: 29 | B45: =IF(C44>0.00001,F45-G45,0) -> #NUM! | C45: =MAX(C44-D45,0) -> #NUM! | D45: =(F45-E45)*-1 -> #NUM! | E45: =IPMT($C$4/12,1,$C$5,C44) -> #NUM! | F45: =PMT($C$4/12,$C$5,$C$3) -> #NUM! | G45: =IF('prijem - EUR'!$I$87=TRUE,IF($C$11>0,0.00025*C44,0),IF('prijem - EUR'!$I$88=TRUE,IF('prijem - EUR'!$F$88>0,0.00025*C44,0),0)) -> 0 | K45: 29 | L45: =IF(M44>0.00001,P45-Q45,0)*-1 -> #DIV/0! | M45: =MAX(M44-N45,0) -> #DIV/0! | N45: =$M$16/$M$5 -> #DIV/0! | O45: =M44*$M$4/12 -> #DIV/0! | P45: =O45+N45 -> #DIV/0! | Q45: =IF('prijem - EUR'!$I$87=TRUE,IF($C$11>0,0.00025*M44,0),IF('prijem - EUR'!$I$88=TRUE,IF('prijem - EUR'!$F$88>0,0.00025*M44*-1,0),0)) -> 0
A46: 30 | B46: =IF(C45>0.00001,F46-G46,0) -> #NUM! | C46: =MAX(C45-D46,0) -> #NUM! | D46: =(F46-E46)*-1 -> #NUM! | E46: =IPMT($C$4/12,1,$C$5,C45) -> #NUM! | F46: =PMT($C$4/12,$C$5,$C$3) -> #NUM! | G46: =IF('prijem - EUR'!$I$87=TRUE,IF($C$11>0,0.00025*C45,0),IF('prijem - EUR'!$I$88=TRUE,IF('prijem - EUR'!$F$88>0,0.00025*C45,0),0)) -> 0 | K46: 30 | L46: =IF(M45>0.00001,P46-Q46,0)*-1 -> #DIV/0! | M46: =MAX(M45-N46,0) -> #DIV/0! | N46: =$M$16/$M$5 -> #DIV/0! | O46: =M45*$M$4/12 -> #DIV/0! | P46: =O46+N46 -> #DIV/0! | Q46: =IF('prijem - EUR'!$I$87=TRUE,IF($C$11>0,0.00025*M45,0),IF('prijem - EUR'!$I$88=TRUE,IF('prijem - EUR'!$F$88>0,0.00025*M45*-1,0),0)) -> 0
A47: 31 | B47: =IF(C46>0.00001,F47-G47,0) -> #NUM! | C47: =MAX(C46-D47,0) -> #NUM! | D47: =(F47-E47)*-1 -> #NUM! | E47: =IPMT($C$4/12,1,$C$5,C46) -> #NUM! | F47: =PMT($C$4/12,$C$5,$C$3) -> #NUM! | G47: =IF('prijem - EUR'!$I$87=TRUE,IF($C$11>0,0.00025*C46,0),IF('prijem - EUR'!$I$88=TRUE,IF('prijem - EUR'!$F$88>0,0.00025*C46,0),0)) -> 0 | K47: 31 | L47: =IF(M46>0.00001,P47-Q47,0)*-1 -> #DIV/0! | M47: =MAX(M46-N47,0) -> #DIV/0! | N47: =$M$16/$M$5 -> #DIV/0! | O47: =M46*$M$4/12 -> #DIV/0! | P47: =O47+N47 -> #DIV/0! | Q47: =IF('prijem - EUR'!$I$87=TRUE,IF($C$11>0,0.00025*M46,0),IF('prijem - EUR'!$I$88=TRUE,IF('prijem - EUR'!$F$88>0,0.00025*M46*-1,0),0)) -> 0
A48: 32 | B48: =IF(C47>0.00001,F48-G48,0) -> #NUM! | C48: =MAX(C47-D48,0) -> #NUM! | D48: =(F48-E48)*-1 -> #NUM! | E48: =IPMT($C$4/12,1,$C$5,C47) -> #NUM! | F48: =PMT($C$4/12,$C$5,$C$3) -> #NUM! | G48: =IF('prijem - EUR'!$I$87=TRUE,IF($C$11>0,0.00025*C47,0),IF('prijem - EUR'!$I$88=TRUE,IF('prijem - EUR'!$F$88>0,0.00025*C47,0),0)) -> 0 | K48: 32 | L48: =IF(M47>0.00001,P48-Q48,0)*-1 -> #DIV/0! | M48: =MAX(M47-N48,0) -> #DIV/0! | N48: =$M$16/$M$5 -> #DIV/0! | O48: =M47*$M$4/12 -> #DIV/0! | P48: =O48+N48 -> #DIV/0! | Q48: =IF('prijem - EUR'!$I$87=TRUE,IF($C$11>0,0.00025*M47,0),IF('prijem - EUR'!$I$88=TRUE,IF('prijem - EUR'!$F$88>0,0.00025*M47*-1,0),0)) -> 0
A49: 33 | B49: =IF(C48>0.00001,F49-G49,0) -> #NUM! | C49: =MAX(C48-D49,0) -> #NUM! | D49: =(F49-E49)*-1 -> #NUM! | E49: =IPMT($C$4/12,1,$C$5,C48) -> #NUM! | F49: =PMT($C$4/12,$C$5,$C$3) -> #NUM! | G49: =IF('prijem - EUR'!$I$87=TRUE,IF($C$11>0,0.00025*C48,0),IF('prijem - EUR'!$I$88=TRUE,IF('prijem - EUR'!$F$88>0,0.00025*C48,0),0)) -> 0 | K49: 33 | L49: =IF(M48>0.00001,P49-Q49,0)*-1 -> #DIV/0! | M49: =MAX(M48-N49,0) -> #DIV/0! | N49: =$M$16/$M$5 -> #DIV/0! | O49: =M48*$M$4/12 -> #DIV/0! | P49: =O49+N49 -> #DIV/0! | Q49: =IF('prijem - EUR'!$I$87=TRUE,IF($C$11>0,0.00025*M48,0),IF('prijem - EUR'!$I$88=TRUE,IF('prijem - EUR'!$F$88>0,0.00025*M48*-1,0),0)) -> 0
A50: 34 | B50: =IF(C49>0.00001,F50-G50,0) -> #NUM! | C50: =MAX(C49-D50,0) -> #NUM! | D50: =(F50-E50)*-1 -> #NUM! | E50: =IPMT($C$4/12,1,$C$5,C49) -> #NUM! | F50: =PMT($C$4/12,$C$5,$C$3) -> #NUM! | G50: =IF('prijem - EUR'!$I$87=TRUE,IF($C$11>0,0.00025*C49,0),IF('prijem - EUR'!$I$88=TRUE,IF('prijem - EUR'!$F$88>0,0.00025*C49,0),0)) -> 0 | K50: 34 | L50: =IF(M49>0.00001,P50-Q50,0)*-1 -> #DIV/0! | M50: =MAX(M49-N50,0) -> #DIV/0! | N50: =$M$16/$M$5 -> #DIV/0! | O50: =M49*$M$4/12 -> #DIV/0! | P50: =O50+N50 -> #DIV/0! | Q50: =IF('prijem - EUR'!$I$87=TRUE,IF($C$11>0,0.00025*M49,0),IF('prijem - EUR'!$I$88=TRUE,IF('prijem - EUR'!$F$88>0,0.00025*M49*-1,0),0)) -> 0
A51: 35 | B51: =IF(C50>0.00001,F51-G51,0) -> #NUM! | C51: =MAX(C50-D51,0) -> #NUM! | D51: =(F51-E51)*-1 -> #NUM! | E51: =IPMT($C$4/12,1,$C$5,C50) -> #NUM! | F51: =PMT($C$4/12,$C$5,$C$3) -> #NUM! | G51: =IF('prijem - EUR'!$I$87=TRUE,IF($C$11>0,0.00025*C50,0),IF('prijem - EUR'!$I$88=TRUE,IF('prijem - EUR'!$F$88>0,0.00025*C50,0),0)) -> 0 | K51: 35 | L51: =IF(M50>0.00001,P51-Q51,0)*-1 -> #DIV/0! | M51: =MAX(M50-N51,0) -> #DIV/0! | N51: =$M$16/$M$5 -> #DIV/0! | O51: =M50*$M$4/12 -> #DIV/0! | P51: =O51+N51 -> #DIV/0! | Q51: =IF('prijem - EUR'!$I$87=TRUE,IF($C$11>0,0.00025*M50,0),IF('prijem - EUR'!$I$88=TRUE,IF('prijem - EUR'!$F$88>0,0.00025*M50*-1,0),0)) -> 0
A52: 36 | B52: =IF(C51>0.00001,F52-G52,0) -> #NUM! | C52: =MAX(C51-D52,0) -> #NUM! | D52: =(F52-E52)*-1 -> #NUM! | E52: =IPMT($C$4/12,1,$C$5,C51) -> #NUM! | F52: =PMT($C$4/12,$C$5,$C$3) -> #NUM! | G52: =IF('prijem - EUR'!$I$87=TRUE,IF($C$11>0,0.00025*C51,0),IF('prijem - EUR'!$I$88=TRUE,IF('prijem - EUR'!$F$88>0,0.00025*C51,0),0)) -> 0 | K52: 36 | L52: =IF(M51>0.00001,P52-Q52,0)*-1 -> #DIV/0! | M52: =MAX(M51-N52,0) -> #DIV/0! | N52: =$M$16/$M$5 -> #DIV/0! | O52: =M51*$M$4/12 -> #DIV/0! | P52: =O52+N52 -> #DIV/0! | Q52: =IF('prijem - EUR'!$I$87=TRUE,IF($C$11>0,0.00025*M51,0),IF('prijem - EUR'!$I$88=TRUE,IF('prijem - EUR'!$F$88>0,0.00025*M51*-1,0),0)) -> 0
... A496: 480 | B496: =IF(C495>0.00001,F496-G496,0) -> #NUM! | C496: =MAX(C495-D496,0) -> #NUM! | D496: =(F496-E496)*-1 -> #NUM! | E496: =IPMT($C$4/12,1,$C$5,C495) -> #NUM! | F496: =PMT($C$4/12,$C$5,$C$3) -> #NUM! | G496: =IF('prijem - EUR'!$I$87=TRUE,IF($C$11>0,0.00025*C495,0),IF('prijem - EUR'!$I$88=TRUE,IF('prijem - EUR'!$F$88>0,0.00025*C495,0),0)) -> 0 | K496: 480 | L496: =IF(M495>0.00001,P496-Q496,0)*-1 -> #DIV/0! | M496: =MAX(M495-N496,0) -> #DIV/0! | N496: =$M$16/$M$5 -> #DIV/0! | O496: =M495*$M$4/12 -> #DIV/0! | P496: =O496+N496 -> #DIV/0! | Q496: =IF('prijem - EUR'!$I$87=TRUE,IF($C$11>0,0.00025*M495,0),IF('prijem - EUR'!$I$88=TRUE,IF('prijem - EUR'!$F$88>0,0.00025*M495*-1,0),0)) -> 0
A497: 481 | K497: 481

Sheet prijem -inna mena
C1: Kalkulačka mHypotéka
D3: Meno klienta
F4: =IF(ISBLANK(F3),"DÁTUM PODANIA!","OK") -> DÁTUM PODANIA!
D5: Číslo žiadosti
D7: Mesačný čistý príjem domácnosti v EUR (prepočtený dle veku) | F7: =F9+F11+F12+F14+F15+F17+F18+F20 -> 0
D8: Mesačný čistý príjem domácnosti v EUR (neprepočtený dle veku) | F8: =F10+F11+F13+F14+F16+F17+F19+F20 -> 0
D9: Čistý príjem žiadateľa č.1 zo závislej činnosti alebo živnosti | F9: =IF(F24="","0",(F10*(F55-MIN(MAX(F24+F55-744,0),F55))/F55)+(F10*0.85*MIN(MAX(F24+F55-744,0),F55)/F55)) -> 0
D10: Čistý príjem žiadateľa č.1 doba určitá/ neurčitá/dohoda/zahraničie
D11: Čistý príjem žiadateľa č.1 z inej činnosti | F11: 0
D12: Čistý príjem žiadateľa č.2 zo závislej činnosti alebo živnosti | F12: =IF(F27="","0",(F13*(F55-MIN(MAX(F27+F55-744,0),F55))/F55)+(F13*0.85*MIN(MAX(F27+F55-744,0),F55)/F55)) -> 0
D13: Čistý príjem žiadateľa č.2 doba určitá/ neurčitá/dohoda/zahraničie
D14: Čistý príjem žiadateľa č.2 z inej činnosti
D15: Čistý príjem žiadateľa č.3 zo závislej činnosti alebo živnosti | F15: =IF(F30="","0",(F16*(F55-MIN(MAX(F30+F55-744,0),F55))/F55)+(F16*0.85*MIN(MAX(F30+F55-744,0),F55)/F55)) -> 0
D16: Čistý príjem žiadateľa č.3 doba určitá/ neurčitá/dohoda/zahraničie
D17: Čistý príjem žiadateľa č.3 z inej činnosti
D18: Čistý príjem žiadateľa č.4 zo závislej činnosti alebo živnosti | F18: =IF(F33="","0",(F19*(F55-MIN(MAX(F33+F55-744,0),F55))/F55)+(F19*0.85*MIN(MAX(F33+F55-744,0),F55)/F55)) -> 0
D19: Čistý príjem žiadateľa č.4 doba určitá/ neurčitá/dohoda/zahraničie
D20: Čistý príjem žiadateľa č.4 z inej činnosti
D21: Počet žiadatelov | F21: 0
D22: Dátum narodenia žiadateľa č. 1
D23: Vek žiadateľa č.1 na limity | F23: =IF(F22="","",YEAR(F3)-YEAR(F22))
D24: Vek žiadateľa č.1 v mesiacoch | F24: =IF(F22="","",(DATEDIF(F22,F3,"M"))+(IF((DAY(F22)-DAY(F3))<=0,0,1)))
D25: Dátum narodenia žiadateľa č. 2
D26: Vek žiadateľa č.2 na limity | F26: =IF(F25="","",YEAR(F3)-YEAR(F25))
D27: Vek žiadateľa č.2 v mesiacoch | F27: =IF(F25="","",(DATEDIF(F25,F3,"M"))+(IF((DAY(F25)-DAY(F3))<=0,0,1)))
D28: Dátum narodenia žiadateľa č. 3
D29: Vek žiadateľa č.3 na limity | F29: =IF(F28="","",YEAR(F3)-YEAR(F28))
D30: Vek žiadateľa č.3 v mesiacoch | F30: =IF(F28="","",(DATEDIF(F28,F3,"M"))+(IF((DAY(F28)-DAY(F3))<=0,0,1)))
D31: Dátum narodenia žiadateľa č. 4
D32: Vek žiadateľa č.4 na limity | F32: =IF(F31="","",YEAR(F3)-YEAR(F31))
D33: Vek žiadateľa č.4 v mesiacoch | F33: =IF(F31="","",(DATEDIF(F31,F3,"M"))+(IF((DAY(F31)-DAY(F3))<=0,0,1)))
D34: Počet žiadatelmi vyživovaných osôb | F34: 0
D35: Number of dependants with applicants | F35: =$F$21+$F$34 -> 0
D36: v tom detí | F36: 0
D37: Available income (including household expenses) | F37: =MAX(0.95*(F7-MAX($F$38,$F$39)),0) -> 0
D38: Expenses - according to Slovak law (COSTS) | F38: =IF($F$35=0,0,0.2*(F7-(210.2+($F$35-$F$36-1)*146.64+($F$36)*95.96+$F$48))+(210.2+($F$35-$F$36-1)*146.64+($F$36)*95.96+$F$48)) -> 0
D39: Expenses - according to the Bank's model (KUGD) | F39: =IF($F$35=0,0,$F$35*((185*($F$35^(-0.4)))^(1-0.4))*(($F$8/$F$35)^(0.4))) -> 0
D43: Výška mesačných splátok splátkových úverov v mBank | F43: 0
D44: Výška mesačných splátok splátkových úverov v iných bankách | F44: 0
D45: Limity kontokorentných úverov | F45: 0
D46: Limity kreditných kariet | F46: 0
D47: Výška mesačných splátok alimentov, exekúcií a iných záväzkov | F47: 0
D48: Prepočtená výška mesačných splátok alimentov, exekúcií a iných záväzkov | F48: =IF($F$47=0,0,IF($F$47>30,$F$47,30)) -> 0
D49: Free income (including liabilities) | F49: =MAX((MIN($F$37,0.75*F7)-$F$43-($F$44*1.2)-0.03*$F$45-0.03*$F$46),0) -> 0
D53: Žiadaná čiastka úveru v EUR
D54: Žiadaná čiastka úveru s Life Insurance | F54: =vyska_uveru_z+F90 -> 0
D55: Žiadaná doba splátkoveho úveru (v mesiacoch) | F55: 0
D56: Hodnota nehnuteľ. ponúkanej ako zabezpečenie úveru v EUR č.1
D57: Volná hodnota nehnuteľnosti č.1
D58: Cena ZP č. 1
D59: Poistné č. 1 ročné | F59: 0
D60: Poistné č. 1 za dobu splácania | F60: =(F59/12)*F55 -> 0
D61: Štandardná hodnota ukazovateľa LtV (% | F61: 0.8
D62: Maximálna hodnota ukazovateľa LtV (%) | F62: =IF(ltv_high_z=80%,100%,IF(ltv_high_z=70%,"80%",IF(C100=2,"75%","90%"))) -> 1
D63: Hodnota nehnuteľ. ponúkanej ako zabezpečenie úveru v EUR č.2
D64: Volná hodnota nehnuteľnosti č.2
D65: Cena ZP č. 2
D66: Poistné č. 2 ročné
D67: Poistné č. 2 za celú dobu splácania | F67: =(F66/12)*F55 -> 0
D68: Štandardná hodnota ukazovateľa LtV (%) | F68: 0.7
D69: Maximálna hodnota ukazovateľa LtV (%) | F69: =IF(F68=80%,100%,IF(F68=70%,"80%",IF(C100=2,"75%","90%"))) -> 80%
D70: Hodnota nehnuteľ. ponúkanej ako zabezpečenie úveru v EUR č.3
D71: Volná hodnota nehnuteľnosti č.3
D72: Cena ZP č. 3
D73: Poistné č. 3 ročné
D74: Poistné č. 3 za celú dobu splácania | F74: =(F73/12)*F55 -> 0
D75: Štandardná hodnota ukazovateľa LtV (%) | F75: 0.65
D76: Maximálna hodnota ukazovateľa LtV (%) | F76: =IF(F75=80%,100%,IF(F75=70%,"80%",IF(C100=2,"75%","90%"))) -> 90%
D77: Skutočná hodnota ukazovateľa LtV (%) | F77: =IFERROR(IF(ISBLANK($F$57)=TRUE,IF(ISBLANK($F$61)=TRUE,0,(F54/(F56+F63+F70))),((zabezpecenie_z-F57+F63-F64+F70-F71+vyska_uveru_LI_z)/(zabezpecenie_z+F63+F70))),0) -> 0
D78: Ročná úroková sadzba (%)
D79: Účelový/Neúčelový úver nebo Štandartná/Neštandartná neh. | F79: 2.49
D80: Příjem v CZK/Příjem v cizí měne
D86: Maximálna dostupná čiastka úveru na základe finančného profilu v EUR | F86: =IFERROR(IF(MIN(F23,F26,F29,F32)<60,(IF(ISBLANK($F$55)=TRUE,"",MAX(($F$49/((E101/12)/(1-(1+(E101/12))^(-$F$55))))/E104,0))),(IF(doba_m_z>60,IF(ISBLANK($F$55)=TRUE,"",MAX(($F$49/((E101/12)/(1-(1+(E101/12))^(-60))))/E104,0)),IF(ISBLANK($F$55)=TRUE,"",MAX(($F$49/((E101/12)/(1-(1+(E101/12))^(-doba_m_z))))/E104,0))))),0) -> 0
D87: Maximalná dostupná čiastka úveru z ohľadom na hodnotu zabezpečenia úveru a maximálnej hodnoty ukazovateľa LtV | F87: =IFERROR(MIN(IF(F7<750,IF(ISBLANK($F$55)=TRUE,"",MIN(0.9*$F$57+0.9*$F$64+0.9*$F$71,$F$86)),IF(ISBLANK($F$55)=TRUE,"",MIN($F$62*$F$57+$F$69*$F$64+$F$76*$F$71,$F$86))),MIN($F$62*$F$57+$F$69*$F$64+$F$76*$F$71,$F$86)),"") -> 0
D89: Vypočítaná anuitná splátka žiadaného úveru | F89: =IF(ISERR(ROUND(IF(ISBLANK($F$55)=TRUE,"",(IF(ISBLANK($F$78)=TRUE,"",$F$54*(($F$78/12)/(1-(1+($F$78/12))^(-$F$55)))))),2)),0,(ROUND(IF(ISBLANK($F$55)=TRUE,"",(IF(ISBLANK($F$78)=TRUE,"",$F$54*(($F$78/12)/(1-(1+($F$78/12))^(-$F$55)))))),2))) -> 0
D90: Poistenie Life Insurance zahrnuté do výšky úveru | F90: =ROUND(IF(I90,F114,0),2) -> 0 | I90: FALSE
D91: Poistenie Life Insurance nezahrnuté do výšky úveru | F91: =ROUND(IF(I91,F115,0),2) -> 0 | I91: FALSE
D92: Prvá klesajúca splátka žiadaného úveru | F92: =IF(ISERR(ROUND(IF(ISBLANK($F$55)=TRUE,"",IF(ISBLANK($F$78)=TRUE,"",$F$54/$F$55+$F$54*$F$78/12)),2)),0,(ROUND(IF(ISBLANK($F$55)=TRUE,"",IF(ISBLANK($F$78)=TRUE,"",$F$54/$F$55+$F$54*$F$78/12)),2))) -> 0
D93: Celk. zaplatená čiastka anuitne splátky (vrátane poplatkov) | F93: =IF(ISERR(RPSN_zahranicie!C13),0,(RPSN_zahranicie!C13)) -> 0
D94: Celk. zaplatená čiastka klesajúce splátky (vrátane poplatkov) | F94: =IF(ISERR(RPSN_zahranicie!N13),0,(RPSN_zahranicie!N13)) -> 0
D95: RPMN pre anuitne splátky | F95: =IF(ISERR(RPSN_zahranicie!C12),0,(RPSN_zahranicie!C12)) -> 0
D96: RPMN pre klesajúce splátky | F96: =IF(ISERR(RPSN_zahranicie!N12),0,(RPSN_zahranicie!N12)) -> 0
C100: 1
C101: 2 | D101: Účel/štandard | E101: =IF(C100=1,0.0384,IF(C100=2,0.042,0.0384)) -> 0.0384
D102: Neúčel/štandard
D103: Účel/neštandard
C104: 2 | D104: Príjem v EUR | E104: =IF(C104=1,1,1.2) -> 1.2
D105: Príjem v cudzej mene
C107: 1 | D107: Katastr 1 | E107: =IF(F57=0,0,IF(ISBLANK(F57)=TRUE,0,66)) -> 0
C108: 2 | D108: Katastr 2 | E108: =IF(F64=0,0,IF(ISBLANK(F64)=TRUE,0,66)) -> 0
C109: 3 | D109: Katastr 3 | E109: =IF(F71=0,0,IF(ISBLANK(F71)=TRUE,0,66)) -> 0
D113: 1) LCI nezahrnuté | E113: LCI nezahrnuté: | F113: =MAX((vyska_uveru_LI_z-zabezpecenie_z*ltv_high_z)*0.045,0) -> 0
E114: LI zahrnuté: | F114: =(0.015/0.985)*vyska_uveru_z -> 0
E115: LI nezahrnuté: | F115: =vyska_uveru_z*0.015 -> 0
D117: 2) LCI zahrnuté, | E117: LCI zahrnuté: | F117: =MAX(0.045/0.955*(vyska_uveru_z-zabezpecenie_z*ltv_high_z),0) -> 0
D118: LI nezahrnuté | E118: LI nezahrnuté: | F118: =#REF!*0.015 -> #REF!
D120: 3) LCI zahrnuté, | E120: LI zahrnuté (LCI = 0): | F120: =0.015/0.985*vyska_uveru_z -> 0
D121: LI zahrnuté | E121: LI zahrnuté (LCI > 0): | F121: =(0.015/0.94)*vyska_uveru_z-(0.015*0.045/0.94)*ltv_high_z*zabezpecenie_z -> 0
E122: ?? LCI > 0 ?? | F122: =F120<(ltv_high_z*zabezpecenie-vyska_uveru_z) -> FALSE
E123: LI zahrnuté final: | F123: =IF(F122,F120,F121) -> 0
...

Sheet RPSN_zahranicie
A2: anuita | L2: klesajuce
B3: vyska uveru | C3: ='prijem -inna mena'!F54 -> 0 | M3: vyska uveru | N3: ='prijem -inna mena'!F54 -> 0
B4: sadzba | C4: =urokova_sadzba_z -> 0 | M4: sadzba | N4: =urokova_sadzba_z -> 0
B5: splatnost | C5: =doba_m_z -> 0 | M5: splatnost | N5: =doba_m_z -> 0
B6: cena ZP | C6: ='prijem -inna mena'!F58+'prijem -inna mena'!F65+'prijem -inna mena'!F72 -> 0 | M6: cena ZP | N6: ='prijem -inna mena'!F58+'prijem -inna mena'!F65+'prijem -inna mena'!F72 -> 0
B7: poistné za rok | C7: ='prijem -inna mena'!F59+'prijem -inna mena'!F66+'prijem -inna mena'!F73 -> 0 | M7: poistné za rok | N7: ='prijem -inna mena'!F59+'prijem -inna mena'!F66+'prijem -inna mena'!F73 -> 0
B8: poistné za celú dobu | C8: ='prijem -inna mena'!F60+'prijem -inna mena'!F67+'prijem -inna mena'!F74 -> 0 | M8: poistné za celú dobu | N8: ='prijem -inna mena'!F60+'prijem -inna mena'!F67+'prijem -inna mena'!F74 -> 0
B9: vklad do katastru | C9: ='prijem -inna mena'!E107+'prijem -inna mena'!E108+'prijem -inna mena'!E109 -> 0 | M9: vklad do katastru | N9: ='prijem -inna mena'!E107+'prijem -inna mena'!E108+'prijem -inna mena'!E109 -> 0
B10: LCI | C10: =LCI_z -> #REF! | M10: LCI | N10: =LCI_z -> #REF!
B11: Life | C11: ='prijem -inna mena'!F90 -> 0 | M11: Life | N11: ='prijem -inna mena'!F90 -> 0
B12: RPSN | C12: =(1+IRR(B16:B496,1%))^12-1 -> #VALUE! | M12: RPSN | N12: =(1+IRR(M16:M496,1%))^12-1 -> #VALUE!
B13: celkova zaplatena | C13: =(SUM(B17:B496)*-1)+C6+C8+C9+H17 -> #NUM! | M13: celkova zaplatena | N13: =(SUM(M17:M496)*-1)+N6+N8+N9+S17 -> #DIV/0!
B15: CF | C15: zostatok | M15: CF | N15: zostatok
A16: mesiac | B16: =C3-C6-C7-C9-C11-H17 -> 0 | C16: =C3 -> 0 | D16: istina | E16: urok | F16: splatka | G16: splatka LI | H16: LI nezapoč | L16: mesiac | M16: =N3-N6-N7-N9-N11-S17 -> 0 | N16: =N3 -> 0 | O16: istina | P16: urok | Q16: splatka | R16: splatka LI | S16: LI nezapoč
A17: 1 | B17: =IF(C16>0.00001,F17-G17,0) -> 0 | C17: =MAX(C16-D17,0) -> #NUM! | D17: =(F17-E17)*-1 -> #NUM! | E17: =IPMT($C$4/12,1,$C$5,C16) -> #NUM! | F17: =PMT($C$4/12,$C$5,$C$3) -> #NUM! | H17: ='prijem -inna mena'!F91 -> 0 | L17: 1 | M17: =IF(N16>0.00001,Q17-R17,0)*-1 -> 0 | N17: =MAX(N16-O17,0) -> #DIV/0! | O17: =$N$16/$N$5 -> #DIV/0! | P17: =N16*$N$4/12 -> 0 | Q17: =P17+O17 -> #DIV/0! | S17: ='prijem -inna mena'!F91 -> 0
A18: 2 | B18: =IF(C17>0.00001,F18-G18,0) -> #NUM! | C18: =MAX(C17-D18,0) -> #NUM! | D18: =(F18-E18)*-1 -> #NUM! | E18: =IPMT($C$4/12,1,$C$5,C17) -> #NUM! | F18: =PMT($C$4/12,$C$5,$C$3) -> #NUM! | L18: 2 | M18: =IF(N17>0.00001,Q18-R18,0)*-1 -> #DIV/0! | N18: =MAX(N17-O18,0) -> #DIV/0! | O18: =$N$16/$N$5 -> #DIV/0! | P18: =N17*$N$4/12 -> #DIV/0! | Q18: =P18+O18 -> #DIV/0!
A19: 3 | B19: =IF(C18>0.00001,F19-G19,0) -> #NUM! | C19: =MAX(C18-D19,0) -> #NUM! | D19: =(F19-E19)*-1 -> #NUM! | E19: =IPMT($C$4/12,1,$C$5,C18) -> #NUM! | F19: =PMT($C$4/12,$C$5,$C$3) -> #NUM! | L19: 3 | M19: =IF(N18>0.00001,Q19-R19,0)*-1 -> #DIV/0! | N19: =MAX(N18-O19,0) -> #DIV/0! | O19: =$N$16/$N$5 -> #DIV/0! | P19: =N18*$N$4/12 -> #DIV/0! | Q19: =P19+O19 -> #DIV/0!
A20: 4 | B20: =IF(C19>0.00001,F20-G20,0) -> #NUM! | C20: =MAX(C19-D20,0) -> #NUM! | D20: =(F20-E20)*-1 -> #NUM! | E20: =IPMT($C$4/12,1,$C$5,C19) -> #NUM! | F20: =PMT($C$4/12,$C$5,$C$3) -> #NUM! | L20: 4 | M20: =IF(N19>0.00001,Q20-R20,0)*-1 -> #DIV/0! | N20: =MAX(N19-O20,0) -> #DIV/0! | O20: =$N$16/$N$5 -> #DIV/0! | P20: =N19*$N$4/12 -> #DIV/0! | Q20: =P20+O20 -> #DIV/0!
A21: 5 | B21: =IF(C20>0.00001,F21-G21,0) -> #NUM! | C21: =MAX(C20-D21,0) -> #NUM! | D21: =(F21-E21)*-1 -> #NUM! | E21: =IPMT($C$4/12,1,$C$5,C20) -> #NUM! | F21: =PMT($C$4/12,$C$5,$C$3) -> #NUM! | L21: 5 | M21: =IF(N20>0.00001,Q21-R21,0)*-1 -> #DIV/0! | N21: =MAX(N20-O21,0) -> #DIV/0! | O21: =$N$16/$N$5 -> #DIV/0! | P21: =N20*$N$4/12 -> #DIV/0! | Q21: =P21+O21 -> #DIV/0!
A22: 6 | B22: =IF(C21>0.00001,F22-G22,0) -> #NUM! | C22: =MAX(C21-D22,0) -> #NUM! | D22: =(F22-E22)*-1 -> #NUM! | E22: =IPMT($C$4/12,1,$C$5,C21) -> #NUM! | F22: =PMT($C$4/12,$C$5,$C$3) -> #NUM! | L22: 6 | M22: =IF(N21>0.00001,Q22-R22,0)*-1 -> #DIV/0! | N22: =MAX(N21-O22,0) -> #DIV/0! | O22: =$N$16/$N$5 -> #DIV/0! | P22: =N21*$N$4/12 -> #DIV/0! | Q22: =P22+O22 -> #DIV/0!
A23: 7 | B23: =IF(C22>0.00001,F23-G23,0) -> #NUM! | C23: =MAX(C22-D23,0) -> #NUM! | D23: =(F23-E23)*-1 -> #NUM! | E23: =IPMT($C$4/12,1,$C$5,C22) -> #NUM! | F23: =PMT($C$4/12,$C$5,$C$3) -> #NUM! | L23: 7 | M23: =IF(N22>0.00001,Q23-R23,0)*-1 -> #DIV/0! | N23: =MAX(N22-O23,0) -> #DIV/0! | O23: =$N$16/$N$5 -> #DIV/0! | P23: =N22*$N$4/12 -> #DIV/0! | Q23: =P23+O23 -> #DIV/0!
A24: 8 | B24: =IF(C23>0.00001,F24-G24,0) -> #NUM! | C24: =MAX(C23-D24,0) -> #NUM! | D24: =(F24-E24)*-1 -> #NUM! | E24: =IPMT($C$4/12,1,$C$5,C23) -> #NUM! | F24: =PMT($C$4/12,$C$5,$C$3) -> #NUM! | L24: 8 | M24: =IF(N23>0.00001,Q24-R24,0)*-1 -> #DIV/0! | N24: =MAX(N23-O24,0) -> #DIV/0! | O24: =$N$16/$N$5 -> #DIV/0! | P24: =N23*$N$4/12 -> #DIV/0! | Q24: =P24+O24 -> #DIV/0!
A25: 9 | B25: =IF(C24>0.00001,F25-G25,0) -> #NUM! | C25: =MAX(C24-D25,0) -> #NUM! | D25: =(F25-E25)*-1 -> #NUM! | E25: =IPMT($C$4/12,1,$C$5,C24) -> #NUM! | F25: =PMT($C$4/12,$C$5,$C$3) -> #NUM! | L25: 9 | M25: =IF(N24>0.00001,Q25-R25,0)*-1 -> #DIV/0! | N25: =MAX(N24-O25,0) -> #DIV/0! | O25: =$N$16/$N$5 -> #DIV/0! | P25: =N24*$N$4/12 -> #DIV/0! | Q25: =P25+O25 -> #DIV/0!
A26: 10 | B26: =IF(C25>0.00001,F26-G26,0) -> #NUM! | C26: =MAX(C25-D26,0) -> #NUM! | D26: =(F26-E26)*-1 -> #NUM! | E26: =IPMT($C$4/12,1,$C$5,C25) -> #NUM! | F26: =PMT($C$4/12,$C$5,$C$3) -> #NUM! | L26: 10 | M26: =IF(N25>0.00001,Q26-R26,0)*-1 -> #DIV/0! | N26: =MAX(N25-O26,0) -> #DIV/0! | O26: =$N$16/$N$5 -> #DIV/0! | P26: =N25*$N$4/12 -> #DIV/0! | Q26: =P26+O26 -> #DIV/0!
A27: 11 | B27: =IF(C26>0.00001,F27-G27,0) -> #NUM! | C27: =MAX(C26-D27,0) -> #NUM! | D27: =(F27-E27)*-1 -> #NUM! | E27: =IPMT($C$4/12,1,$C$5,C26) -> #NUM! | F27: =PMT($C$4/12,$C$5,$C$3) -> #NUM! | L27: 11 | M27: =IF(N26>0.00001,Q27-R27,0)*-1 -> #DIV/0! | N27: =MAX(N26-O27,0) -> #DIV/0! | O27: =$N$16/$N$5 -> #DIV/0! | P27: =N26*$N$4/12 -> #DIV/0! | Q27: =P27+O27 -> #DIV/0!
A28: 12 | B28: =IF(C27>0.00001,F28-G28,0) -> #NUM! | C28: =MAX(C27-D28,0) -> #NUM! | D28: =(F28-E28)*-1 -> #NUM! | E28: =IPMT($C$4/12,1,$C$5,C27) -> #NUM! | F28: =PMT($C$4/12,$C$5,$C$3) -> #NUM! | L28: 12 | M28: =IF(N27>0.00001,Q28-R28,0)*-1 -> #DIV/0! | N28: =MAX(N27-O28,0) -> #DIV/0! | O28: =$N$16/$N$5 -> #DIV/0! | P28: =N27*$N$4/12 -> #DIV/0! | Q28: =P28+O28 -> #DIV/0!
A29: 13 | B29: =IF(C28>0.00001,F29-G29,0) -> #NUM! | C29: =MAX(C28-D29,0) -> #NUM! | D29: =(F29-E29)*-1 -> #NUM! | E29: =IPMT($C$4/12,1,$C$5,C28) -> #NUM! | F29: =PMT($C$4/12,$C$5,$C$3) -> #NUM! | L29: 13 | M29: =IF(N28>0.00001,Q29-R29,0)*-1 -> #DIV/0! | N29: =MAX(N28-O29,0) -> #DIV/0! | O29: =$N$16/$N$5 -> #DIV/0! | P29: =N28*$N$4/12 -> #DIV/0! | Q29: =P29+O29 -> #DIV/0!
... A40: 24 | B40: =IF(C39>0.00001,F40-G40,0) -> #NUM! | C40: =MAX(C39-D40,0) -> #NUM! | D40: =(F40-E40)*-1 -> #NUM! | E40: =IPMT($C$4/12,1,$C$5,C39) -> #NUM! | F40: =PMT($C$4/12,$C$5,$C$3) -> #NUM! | L40: 24 | M40: =IF(N39>0.00001,Q40-R40,0)*-1 -> #DIV/0! | N40: =MAX(N39-O40,0) -> #DIV/0! | O40: =$N$16/$N$5 -> #DIV/0! | P40: =N39*$N$4/12 -> #DIV/0! | Q40: =P40+O40 -> #DIV/0!
A41: 25 | B41: =IF(C40>0.00001,F41-G41,0) -> #NUM! | C41: =MAX(C40-D41,0) -> #NUM! | D41: =(F41-E41)*-1 -> #NUM! | E41: =IPMT($C$4/12,1,$C$5,C40) -> #NUM! | F41: =PMT($C$4/12,$C$5,$C$3) -> #NUM! | G41: =IF('prijem -inna mena'!$I$90=TRUE,IF($C$11>0,0.00025*C40,0),IF('prijem -inna mena'!$I$91=TRUE,IF('prijem -inna mena'!$F$91>0,0.00025*C40,0),0)) -> 0 | L41: 25 | M41: =IF(N40>0.00001,Q41-R41,0)*-1 -> #DIV/0! | N41: =MAX(N40-O41,0) -> #DIV/0! | O41: =$N$16/$N$5 -> #DIV/0! | P41: =N40*$N$4/12 -> #DIV/0! | Q41: =P41+O41 -> #DIV/0! | R41: =IF('prijem -inna mena'!$I$90=TRUE,IF($C$11>0,0.00025*N40,0),IF('prijem -inna mena'!$I$91=TRUE,IF('prijem -inna mena'!$F$91>0,0.00025*N40*-1,0),0)) -> 0
A42: 26 | B42: =IF(C41>0.00001,F42-G42,0) -> #NUM! | C42: =MAX(C41-D42,0) -> #NUM! | D42: =(F42-E42)*-1 -> #NUM! | E42: =IPMT($C$4/12,1,$C$5,C41) -> #NUM! | F42: =PMT($C$4/12,$C$5,$C$3) -> #NUM! | G42: =IF('prijem -inna mena'!$I$90=TRUE,IF($C$11>0,0.00025*C41,0),IF('prijem -inna mena'!$I$91=TRUE,IF('prijem -inna mena'!$F$91>0,0.00025*C41,0),0)) -> 0 | L42: 26 | M42: =IF(N41>0.00001,Q42-R42,0)*-1 -> #DIV/0! | N42: =MAX(N41-O42,0) -> #DIV/0! | O42: =$N$16/$N$5 -> #DIV/0! | P42: =N41*$N$4/12 -> #DIV/0! | Q42: =P42+O42 -> #DIV/0! | R42: =IF('prijem -inna mena'!$I$90=TRUE,IF($C$11>0,0.00025*N41,0),IF('prijem -inna mena'!$I$91=TRUE,IF('prijem -inna mena'!$F$91>0,0.00025*N41*-1,0),0)) -> 0
A43: 27 | B43: =IF(C42>0.00001,F43-G43,0) -> #NUM! | C43: =MAX(C42-D43,0) -> #NUM! | D43: =(F43-E43)*-1 -> #NUM! | E43: =IPMT($C$4/12,1,$C$5,C42) -> #NUM! | F43: =PMT($C$4/12,$C$5,$C$3) -> #NUM! | G43: =IF('prijem -inna mena'!$I$90=TRUE,IF($C$11>0,0.00025*C42,0),IF('prijem -inna mena'!$I$91=TRUE,IF('prijem -inna mena'!$F$91>0,0.00025*C42,0),0)) -> 0 | L43: 27 | M43: =IF(N42>0.00001,Q43-R43,0)*-1 -> #DIV/0! | N43: =MAX(N42-O43,0) -> #DIV/0! | O43: =$N$16/$N$5 -> #DIV/0! | P43: =N42*$N$4/12 -> #DIV/0! | Q43: =P43+O43 -> #DIV/0! | R43: =IF('prijem -inna mena'!$I$90=TRUE,IF($C$11>0,0.00025*N42,0),IF('prijem -inna mena'!$I$91=TRUE,IF('prijem -inna mena'!$F$91>0,0.00025*N42*-1,0),0)) -> 0
A44: 28 | B44: =IF(C43>0.00001,F44-G44,0) -> #NUM! | C44: =MAX(C43-D44,0) -> #NUM! | D44: =(F44-E44)*-1 -> #NUM! | E44: =IPMT($C$4/12,1,$C$5,C43) -> #NUM! | F44: =PMT($C$4/12,$C$5,$C$3) -> #NUM! | G44: =IF('prijem -inna mena'!$I$90=TRUE,IF($C$11>0,0.00025*C43,0),IF('prijem -inna mena'!$I$91=TRUE,IF('prijem -inna mena'!$F$91>0,0.00025*C43,0),0)) -> 0 | L44: 28 | M44: =IF(N43>0.00001,Q44-R44,0)*-1 -> #DIV/0! | N44: =MAX(N43-O44,0) -> #DIV/0! | O44: =$N$16/$N$5 -> #DIV/0! | P44: =N43*$N$4/12 -> #DIV/0! | Q44: =P44+O44 -> #DIV/0! | R44: =IF('prijem -inna mena'!$I$90=TRUE,IF($C$11>0,0.00025*N43,0),IF('prijem -inna mena'!$I$91=TRUE,IF('prijem -inna mena'!$F$91>0,0.00025*N43*-1,0),0)) -> 0
A45: 29 | B45: =IF(C44>0.00001,F45-G45,0) -> #NUM! | C45: =MAX(C44-D45,0) -> #NUM! | D45: =(F45-E45)*-1 -> #NUM! | E45: =IPMT($C$4/12,1,$C$5,C44) -> #NUM! | F45: =PMT($C$4/12,$C$5,$C$3) -> #NUM! | G45: =IF('prijem -inna mena'!$I$90=TRUE,IF($C$11>0,0.00025*C44,0),IF('prijem -inna mena'!$I$91=TRUE,IF('prijem -inna mena'!$F$91>0,0.00025*C44,0),0)) -> 0 | L45: 29 | M45: =IF(N44>0.00001,Q45-R45,0)*-1 -> #DIV/0! | N45: =MAX(N44-O45,0) -> #DIV/0! | O45: =$N$16/$N$5 -> #DIV/0! | P45: =N44*$N$4/12 -> #DIV/0! | Q45: =P45+O45 -> #DIV/0! | R45: =IF('prijem -inna mena'!$I$90=TRUE,IF($C$11>0,0.00025*N44,0),IF('prijem -inna mena'!$I$91=TRUE,IF('prijem -inna mena'!$F$91>0,0.00025*N44*-1,0),0)) -> 0
A46: 30 | B46: =IF(C45>0.00001,F46-G46,0) -> #NUM! | C46: =MAX(C45-D46,0) -> #NUM! | D46: =(F46-E46)*-1 -> #NUM! | E46: =IPMT($C$4/12,1,$C$5,C45) -> #NUM! | F46: =PMT($C$4/12,$C$5,$C$3) -> #NUM! | G46: =IF('prijem -inna mena'!$I$90=TRUE,IF($C$11>0,0.00025*C45,0),IF('prijem -inna mena'!$I$91=TRUE,IF('prijem -inna mena'!$F$91>0,0.00025*C45,0),0)) -> 0 | L46: 30 | M46: =IF(N45>0.00001,Q46-R46,0)*-1 -> #DIV/0! | N46: =MAX(N45-O46,0) -> #DIV/0! | O46: =$N$16/$N$5 -> #DIV/0! | P46: =N45*$N$4/12 -> #DIV/0! | Q46: =P46+O46 -> #DIV/0! | R46: =IF('prijem -inna mena'!$I$90=TRUE,IF($C$11>0,0.00025*N45,0),IF('prijem -inna mena'!$I$91=TRUE,IF('prijem -inna mena'!$F$91>0,0.00025*N45*-1,0),0)) -> 0
A47: 31 | B47: =IF(C46>0.00001,F47-G47,0) -> #NUM! | C47: =MAX(C46-D47,0) -> #NUM! | D47: =(F47-E47)*-1 -> #NUM! | E47: =IPMT($C$4/12,1,$C$5,C46) -> #NUM! | F47: =PMT($C$4/12,$C$5,$C$3) -> #NUM! | G47: =IF('prijem -inna mena'!$I$90=TRUE,IF($C$11>0,0.00025*C46,0),IF('prijem -inna mena'!$I$91=TRUE,IF('prijem -inna mena'!$F$91>0,0.00025*C46,0),0)) -> 0 | L47: 31 | M47: =IF(N46>0.00001,Q47-R47,0)*-1 -> #DIV/0! | N47: =MAX(N46-O47,0) -> #DIV/0! | O47: =$N$16/$N$5 -> #DIV/0! | P47: =N46*$N$4/12 -> #DIV/0! | Q47: =P47+O47 -> #DIV/0! | R47: =IF('prijem -inna mena'!$I$90=TRUE,IF($C$11>0,0.00025*N46,0),IF('prijem -inna mena'!$I$91=TRUE,IF('prijem -inna mena'!$F$91>0,0.00025*N46*-1,0),0)) -> 0
A48: 32 | B48: =IF(C47>0.00001,F48-G48,0) -> #NUM! | C48: =MAX(C47-D48,0) -> #NUM! | D48: =(F48-E48)*-1 -> #NUM! | E48: =IPMT($C$4/12,1,$C$5,C47) -> #NUM! | F48: =PMT($C$4/12,$C$5,$C$3) -> #NUM! | G48: =IF('prijem -inna mena'!$I$90=TRUE,IF($C$11>0,0.00025*C47,0),IF('prijem -inna mena'!$I$91=TRUE,IF('prijem -inna mena'!$F$91>0,0.00025*C47,0),0)) -> 0 | L48: 32 | M48: =IF(N47>0.00001,Q48-R48,0)*-1 -> #DIV/0! | N48: =MAX(N47-O48,0) -> #DIV/0! | O48: =$N$16/$N$5 -> #DIV/0! | P48: =N47*$N$4/12 -> #DIV/0! | Q48: =P48+O48 -> #DIV/0! | R48: =IF('prijem -inna mena'!$I$90=TRUE,IF($C$11>0,0.00025*N47,0),IF('prijem -inna mena'!$I$91=TRUE,IF('prijem -inna mena'!$F$91>0,0.00025*N47*-1,0),0)) -> 0
A49: 33 | B49: =IF(C48>0.00001,F49-G49,0) -> #NUM! | C49: =MAX(C48-D49,0) -> #NUM! | D49: =(F49-E49)*-1 -> #NUM! | E49: =IPMT($C$4/12,1,$C$5,C48) -> #NUM! | F49: =PMT($C$4/12,$C$5,$C$3) -> #NUM! | G49: =IF('prijem -inna mena'!$I$90=TRUE,IF($C$11>0,0.00025*C48,0),IF('prijem -inna mena'!$I$91=TRUE,IF('prijem -inna mena'!$F$91>0,0.00025*C48,0),0)) -> 0 | L49: 33 | M49: =IF(N48>0.00001,Q49-R49,0)*-1 -> #DIV/0! | N49: =MAX(N48-O49,0) -> #DIV/0! | O49: =$N$16/$N$5 -> #DIV/0! | P49: =N48*$N$4/12 -> #DIV/0! | Q49: =P49+O49 -> #DIV/0! | R49: =IF('prijem -inna mena'!$I$90=TRUE,IF($C$11>0,0.00025*N48,0),IF('prijem -inna mena'!$I$91=TRUE,IF('prijem -inna mena'!$F$91>0,0.00025*N48*-1,0),0)) -> 0
A50: 34 | B50: =IF(C49>0.00001,F50-G50,0) -> #NUM! | C50: =MAX(C49-D50,0) -> #NUM! | D50: =(F50-E50)*-1 -> #NUM! | E50: =IPMT($C$4/12,1,$C$5,C49) -> #NUM! | F50: =PMT($C$4/12,$C$5,$C$3) -> #NUM! | G50: =IF('prijem -inna mena'!$I$90=TRUE,IF($C$11>0,0.00025*C49,0),IF('prijem -inna mena'!$I$91=TRUE,IF('prijem -inna mena'!$F$91>0,0.00025*C49,0),0)) -> 0 | L50: 34 | M50: =IF(N49>0.00001,Q50-R50,0)*-1 -> #DIV/0! | N50: =MAX(N49-O50,0) -> #DIV/0! | O50: =$N$16/$N$5 -> #DIV/0! | P50: =N49*$N$4/12 -> #DIV/0! | Q50: =P50+O50 -> #DIV/0! | R50: =IF('prijem -inna mena'!$I$90=TRUE,IF($C$11>0,0.00025*N49,0),IF('prijem -inna mena'!$I$91=TRUE,IF('prijem -inna mena'!$F$91>0,0.00025*N49*-1,0),0)) -> 0
A51: 35 | B51: =IF(C50>0.00001,F51-G51,0) -> #NUM! | C51: =MAX(C50-D51,0) -> #NUM! | D51: =(F51-E51)*-1 -> #NUM! | E51: =IPMT($C$4/12,1,$C$5,C50) -> #NUM! | F51: =PMT($C$4/12,$C$5,$C$3) -> #NUM! | G51: =IF('prijem -inna mena'!$I$90=TRUE,IF($C$11>0,0.00025*C50,0),IF('prijem -inna mena'!$I$91=TRUE,IF('prijem -inna mena'!$F$91>0,0.00025*C50,0),0)) -> 0 | L51: 35 | M51: =IF(N50>0.00001,Q51-R51,0)*-1 -> #DIV/0! | N51: =MAX(N50-O51,0) -> #DIV/0! | O51: =$N$16/$N$5 -> #DIV/0! | P51: =N50*$N$4/12 -> #DIV/0! | Q51: =P51+O51 -> #DIV/0! | R51: =IF('prijem -inna mena'!$I$90=TRUE,IF($C$11>0,0.00025*N50,0),IF('prijem -inna mena'!$I$91=TRUE,IF('prijem -inna mena'!$F$91>0,0.00025*N50*-1,0),0)) -> 0
A52: 36 | B52: =IF(C51>0.00001,F52-G52,0) -> #NUM! | C52: =MAX(C51-D52,0) -> #NUM! | D52: =(F52-E52)*-1 -> #NUM! | E52: =IPMT($C$4/12,1,$C$5,C51) -> #NUM! | F52: =PMT($C$4/12,$C$5,$C$3) -> #NUM! | G52: =IF('prijem -inna mena'!$I$90=TRUE,IF($C$11>0,0.00025*C51,0),IF('prijem -inna mena'!$I$91=TRUE,IF('prijem -inna mena'!$F$91>0,0.00025*C51,0),0)) -> 0 | L52: 36 | M52: =IF(N51>0.00001,Q52-R52,0)*-1 -> #DIV/0! | N52: =MAX(N51-O52,0) -> #DIV/0! | O52: =$N$16/$N$5 -> #DIV/0! | P52: =N51*$N$4/12 -> #DIV/0! | Q52: =P52+O52 -> #DIV/0! | R52: =IF('prijem -inna mena'!$I$90=TRUE,IF($C$11>0,0.00025*N51,0),IF('prijem -inna mena'!$I$91=TRUE,IF('prijem -inna mena'!$F$91>0,0.00025*N51*-1,0),0)) -> 0
... A496: 480 | B496: =IF(C495>0.00001,F496-G496,0) -> #NUM! | C496: =MAX(C495-D496,0) -> #NUM! | D496: =(F496-E496)*-1 -> #NUM! | E496: =IPMT($C$4/12,1,$C$5,C495) -> #NUM! | F496: =PMT($C$4/12,$C$5,$C$3) -> #NUM! | G496: =IF('prijem -inna mena'!$I$90=TRUE,IF($C$11>0,0.00025*C495,0),IF('prijem -inna mena'!$I$91=TRUE,IF('prijem -inna mena'!$F$91>0,0.00025*C495,0),0)) -> 0 | L496: 480 | M496: =IF(N495>0.00001,Q496-R496,0)*-1 -> #DIV/0! | N496: =MAX(N495-O496,0) -> #DIV/0! | O496: =$N$16/$N$5 -> #DIV/0! | P496: =N495*$N$4/12 -> #DIV/0! | Q496: =P496+O496 -> #DIV/0! | R496: =IF('prijem -inna mena'!$I$90=TRUE,IF($C$11>0,0.00025*N495,0),IF('prijem -inna mena'!$I$91=TRUE,IF('prijem -inna mena'!$F$91>0,0.00025*N495*-1,0),0)) -> 0
A497: 481 | L497: 481

Sheet prijem - EUR-viac-domacnosti
C1: Kalkulačka mHypotéka
D3: Dátum zadania do systému
F4: =IF(ISBLANK(F3),"DÁTUM PODANIA!","OK") -> DÁTUM PODANIA!
D5: Číslo žiadosti
D6: Domácnosť č. 1
D8: Mesačný čistý príjem domácnosti v EUR No.1 | F8: =MAX(F9+F12+F15-F10-F13-F16,0) -> 0 | I8: MIN_VĚK_1
D9: Čistý príjem žiadateľa č.1 | F9: 0 | I9: =IF(F18=3,MIN(F20,F22,F24),IF(F18=2,MIN(F20,F22),F20)) -> 0
D10: z toho príjem z výživného a sirotského dôchodku | F10: 0
D11: Náklady bývania žiadateľa č. 1 | F11: 0
D12: Čistý príjem žiadateľa č.2 | F12: 0
D13: z toho príjem z výživného a sirotského dôchodku | F13: 0
D14: Náklady bývania žiadateľa č. 2 | F14: 0
D15: Čistý príjem žiadateľa č.3 | F15: 0
D16: z toho príjem z výživného a sirotského dôchodku | F16: 0
D17: Náklady bývania žiadateľa č. 3 | F17: 0
D18: Počet žiadatelov
D19: Dátum narodenia žiadateľa č. 1 | I19: =IF(F20<41,8,IF(F20+F84/12<65,8,MAX(8-0.25*(F20-40),3))) -> 8
D20: Vek žiadateľa č. 1 na limity | F20: =IF(F19="",0,IF(AND(DAY(F3)=DAY(F19),MONTH(F3)=MONTH(F19)),YEAR(F3)-YEAR(F19),FLOOR(YEARFRAC(F19,F3,1),1))) -> 0
D21: Dátum narodenia žiadateľa č. 2 | I21: =IF(F22<41,8,IF(F22+F84/12<65,8,MAX(8-0.25*(F22-40),3))) -> 8
D22: Vek žiadateľa č.2 na limity | F22: =IF(F21="",0,IF(AND(DAY(F3)=DAY(F21),MONTH(F3)=MONTH(F21)),YEAR(F3)-YEAR(F21),FLOOR(YEARFRAC(F21,F3,1),1))) -> 0
D23: Dátum narodenia žiadateľa č. 3 | I23: =IF(F24<41,8,IF(F24+F84/12<65,8,MAX(8-0.25*(F24-40),3))) -> 8
D24: Vek žiadateľa č.3 na limity | F24: =IF(F23="",0,IF(AND(DAY(F3)=DAY(F23),MONTH(F3)=MONTH(F23)),YEAR(F3)-YEAR(F23),FLOOR(YEARFRAC(F23,F3,1),1))) -> 0
D25: Počet žiadatelmi vyživovaných osôb
D26: Number of dependants with applicants | F26: =F18+F25 -> 0
D27: v tom detí
D28: KUGD_GOSP_1 | F28: =IF($F$26=0,0,MAX($F$26*((185*($F$26^(-0.4)))^(1-0.4))*((((F9+F12+F15)*F66/(F9+F12+F15+F38+F41+F44))/$F$26)^(0.4)),0)) -> 0
D30: Výška mesačných splátok splátkových úverov
D31: Limity kontokorentných úverov
D32: Limity kreditných kariet
D33: Výška mesačných splátok alimentov, exekúcií a iných záväzkov
D35: Domácnosť č. 2
D37: Mesačný čistý príjem domácnosti v EUR No.2 | F37: =MAX(F38+F41+F44-F39-F42-F45,0) -> 0 | I37: MIN_VĚK_2
D38: Čistý príjem žiadateľa č.1 | F38: 0 | I38: =IF(F47=3,MIN(F49,F51,F53),IF(F47=2,MIN(F49,F51),F49)) -> 0
D39: z toho príjem z výživného a sirotského dôchodku | F39: 0
D40: Náklady bývania žiadateľa č. 1 | F40: 0
D41: Čistý príjem žiadateľa č.2 | F41: 0
D42: z toho príjem z výživného a sirotského dôchodku | F42: 0
D43: Náklady bývania žiadateľa č. 2
D44: Čistý príjem žiadateľa č.3 | F44: 0
D45: z toho príjem z výživného a sirotského dôchodku | F45: 0
D46: Náklady bývania žiadateľa č. 3
D47: Počet žiadatelov
D48: Dátum narodenia žiadateľa č. 1 | I48: =IF(F49<41,8,IF(F49+F84/12<65,8,MAX(8-0.25*(F49-40),3))) -> 8
D49: Vek žiadateľa č.1 na limity | F49: =IF(F48="",0,IF(AND(DAY(F3)=DAY(F48),MONTH(F3)=MONTH(F48)),YEAR(F3)-YEAR(F48),FLOOR(YEARFRAC(F48,F3,1),1))) -> 0
D50: Dátum narodenia žiadateľa č. 2 | I50: =IF(F51<41,8,IF(F51+F84/12<65,8,MAX(8-0.25*(F51-40),3))) -> 8
D51: Vek žiadateľa č.2 na limity | F51: =IF(F50="",0,IF(AND(DAY(F3)=DAY(F50),MONTH(F3)=MONTH(F50)),YEAR(F3)-YEAR(F50),FLOOR(YEARFRAC(F50,F3,1),1))) -> 0
D52: Dátum narodenia žiadateľa č. 3 | I52: =IF(F53<41,8,IF(F53+F84/12<65,8,MAX(8-0.25*(F53-40),3))) -> 8
D53: Vek žiadateľa č.3 na limity | F53: =IF(F52="",0,IF(AND(DAY(F3)=DAY(F52),MONTH(F3)=MONTH(F52)),YEAR(F3)-YEAR(F52),FLOOR(YEARFRAC(F52,F3,1),1))) -> 0
D54: Počet žiadatelmi vyživovaných osôb | F54: 0
D55: Number of dependants with applicants | F55: =F47+F54 -> 0
D56: v tom detí | F56: 0
D57: KUGD_GOSP_2 | F57: =IF($F$55=0,0,MAX($F$55*((185*($F$55^(-0.4)))^(1-0.4))*((((F38+F41+F44)*F66/(F9+F12+F15+F38+F41+F44))/$F$55)^(0.4)),0)) -> 0
D59: Výška mesačných splátok splátkových úverov
D60: Limity kontokorentných úverov
D61: Limity kreditných kariet
D62: Výška mesačných splátok alimentov, exekúcií a iných záväzkov
D66: Mesačný čistý príjem domácnosti v EUR | F66: =F8+F37 -> 0
D67: Number of dependants with applicants | F67: =F26+F55 -> 0
D68: Number of children | F68: =F27+F56 -> 0
D69: Prepočtená výška mesačných splátok alimentov, exekúcií a iných záväzkov | F69: =IF(($F$33+$F$62)=0,0,IF(($F$33+$F$62)>30,($F$33+$F$62),30)) -> 0
D70: Expenses - according to Slovak law (COSTS) | F70: =IF($F$67=0,0,(284.13+MAX(($F$67-$F$68-1)*198.22+($F$68)*129.74-F10-F13-F16-F39-F42-F45,0)+$F$69)) -> 0
D71: Expenses - according to Slovak law (COSTS) + Housing cost | F71: =IF($F$67=0,0,($F$70+F11+F14+F17+F40+F43+F46)) -> 0
D72: KUGD_GOSP | F72: =IF($F$67=0,0,MAX($F$67*((185*($F$67^(-0.4)))^(1-0.4))*(($F$66/$F$67)^(0.4)),0)) -> 0
D73: KUGD | F73: =MAX(F28+F57,F72) -> 0
D74: Available income (including household expenses) | F74: =MAX(0.95*(F66-MAX($F$71,$F$73)),0) -> 0
D75: Výška mesačných splátok splátkových úverov | F75: =F30+F59 -> 0
D76: Limity kontokorentných úverov | F76: =F31+F60 -> 0
D77: Limity kreditných kariet | F77: =F32+F61 -> 0
D78: Free income (including liabilities) | F78: =MAX((MIN($F$74,0.75*F66)-$F$75-0.03*$F$76-0.03*$F$77),0) -> 0
D82: Žiadaná čiastka úveru v EUR | F82: 0
D83: Žiadaná čiastka úveru s Life Insurance | F83: =F82+F120 -> 0
D84: Žiadaná doba splátkoveho úveru (v mesiacoch) | F84: 0
D85: Hodnota nehnuteľ. ponúkanej ako zabezpečenie úveru v EUR č.1
D86: Volná hodnota nehnuteľnosti č.1
D87: Cena ZP č. 1
D88: Poistné č. 1 ročné
D89: Poistné č. 1 za dobu splácania | F89: =(F88/12)*F84 -> 0
D90: Štandardná hodnota ukazovateľa LtV (% | F90: 0.8
D91: Maximálna hodnota ukazovateľa LtV (%) | F91: =IF(F90=80%,100%,IF(F90=70%,"80%",IF(C132=2,"75%","90%"))) -> 1
D92: Hodnota nehnuteľ. ponúkanej ako zabezpečenie úveru v EUR č.2
D93: Volná hodnota nehnuteľnosti č.2
D94: Cena ZP č. 2
D95: Poistné č. 2 ročné
D96: Poistné č. 2 za celú dobu splácania | F96: =(F95/12)*F84 -> 0
D97: Štandardná hodnota ukazovateľa LtV (%) | F97: 0.65
D98: Maximálna hodnota ukazovateľa LtV (%) | F98: =IF(F97=80%,100%,IF(F97=70%,"80%",IF(C132=2,"75%","90%"))) -> 90%
D99: Hodnota nehnuteľ. ponúkanej ako zabezpečenie úveru v EUR č.3
D100: Volná hodnota nehnuteľnosti č.3
D101: Cena ZP č. 3
D102: Poistné č. 3 ročné
D103: Poistné č. 3 za celú dobu splácania | F103: =(F102/12)*F84 -> 0
D104: Štandardná hodnota ukazovateľa LtV (%) | F104: 0.65
D105: Maximálna hodnota ukazovateľa LtV (%) | F105: =IF(F104=80%,100%,IF(F104=70%,"80%",IF(C132=2,"75%","90%"))) -> 90%
D106: Skutočná hodnota ukazovateľa LtV (%) | F106: =IFERROR(IF(ISBLANK($F$86)=TRUE,IF(ISBLANK($F$90)=TRUE,0,(F83/(F85+F92+F99))),((F85-F86+F92-F93+F99-F100+F83)/(F85+F92+F99))),0) -> 0
D107: Ročná úroková sadzba (%) | F107: 0
D108: Účelový / Neúčelový úver | F108: 2
D109: Příjem v CZK/Příjem v cizí měne
D115: Maximálna dostupná čiastka úveru na základe finančného profilu v EUR | F115: =IFERROR(IF(MIN(I9,I38)<60,(IF(ISBLANK($F$84)=TRUE,0,MIN(MAX($F$78/((E132/12)/(1-(1+(E132/12))^(-MIN($F$84,360)))),0),F66/(1/$F$84+F107/12))/E135)),(IF($F$84>60,IF(ISBLANK($F$84)=TRUE,0,MIN(MAX($F$78/((E132/12)/(1-(1+(E132/12))^(-60))),0),F66/(1/$F$84+F107/12))/E135),IF(ISBLANK($F$84)=TRUE,0,MIN(MAX($F$78/((E132/12)/(1-(1+(E132/12))^(-$F$84))),0),F66/(1/$F$84+F107/12))/E135)))),0) -> 0
D116: Maximalná dostupná čiastka úveru z ohľadom na hodnotu zabezpečenia úveru a maximálnej hodnoty ukazovateľa LtV | F116: =IFERROR(MIN(IF(F66<750,IF(ISBLANK($F$84)=TRUE,"",MIN(0.9*$F$86+0.9*F93+0.9*F100, $F$115)),IF(ISBLANK($F$84)=TRUE,"",MIN($F$91*$F$86+F93*F98+F100*F105, $F$115))),MIN($F$91*$F$86+F93*F98+F100*F105, $F$115)),"") -> 0
D118: Vypočítaná anuitná splátka žiadaného úveru | F118: =IF(ISERR(ROUND(IF(ISBLANK($F$84)=TRUE,"",(IF(ISBLANK($F$107)=TRUE,"",$F$83*(($F$107/12)/(1-(1+($F$107/12))^(-$F$84)))))),2)),0,ROUND(IF(ISBLANK($F$84)=TRUE,"",(IF(ISBLANK($F$107)=TRUE,"",$F$83*(($F$107/12)/(1-(1+($F$107/12))^(-$F$84)))))),2)) -> 0
...

Sheet RPMN - prijem - EUR-vice-domac
A2: anuita | L2: klesajuce
B3: vyska uveru | C3: ='prijem - EUR-viac-domacnosti'!F83 -> 0 | M3: vyska uveru | N3: ='prijem - EUR-viac-domacnosti'!F83 -> 0
B4: sadzba | C4: ='prijem - EUR-viac-domacnosti'!F107 -> 0 | M4: sadzba | N4: ='prijem - EUR-viac-domacnosti'!F107 -> 0
B5: splatnost | C5: ='prijem - EUR-viac-domacnosti'!F84 -> 0 | M5: splatnost | N5: ='prijem - EUR-viac-domacnosti'!F84 -> 0
B6: cena ZP | C6: ='prijem - EUR-viac-domacnosti'!F87+'prijem - EUR-viac-domacnosti'!F94+'prijem - EUR-viac-domacnosti'!F101 -> 0 | M6: cena ZP | N6: ='prijem - EUR-viac-domacnosti'!F87+'prijem - EUR-viac-domacnosti'!F94+'prijem - EUR-viac-domacnosti'!F101 -> 0
B7: poistné za rok | C7: ='prijem - EUR-viac-domacnosti'!F88+'prijem - EUR-viac-domacnosti'!F95+'prijem - EUR-viac-domacnosti'!F102 -> 0 | M7: poistné za rok | N7: ='prijem - EUR-viac-domacnosti'!F88+'prijem - EUR-viac-domacnosti'!F95+'prijem - EUR-viac-domacnosti'!F102 -> 0
B8: poistné za celú dobu | C8: ='prijem - EUR-viac-domacnosti'!F89+'prijem - EUR-viac-domacnosti'!F96+'prijem - EUR-viac-domacnosti'!F103 -> 0 | M8: poistné za celú dobu | N8: ='prijem - EUR-viac-domacnosti'!F89+'prijem - EUR-viac-domacnosti'!F96+'prijem - EUR-viac-domacnosti'!F103 -> 0
B9: vklad do katastru | C9: ='prijem - EUR-viac-domacnosti'!E138+'prijem - EUR-viac-domacnosti'!E139+'prijem - EUR-viac-domacnosti'!E140 -> 0 | M9: vklad do katastru | N9: ='prijem - EUR-viac-domacnosti'!E138+'prijem - EUR-viac-domacnosti'!E139+'prijem - EUR-viac-domacnosti'!E140 -> 0
B10: LCI | C10: #REF! | M10: LCI | N10: #REF!
B11: Life | C11: ='prijem - EUR-viac-domacnosti'!F120 -> 0 | M11: Life | N11: ='prijem - EUR-viac-domacnosti'!F120 -> 0
B12: RPMN | C12: =(1+IRR(B16:B496,1%))^12-1 -> #VALUE! | M12: RPMN | N12: =(1+IRR(M16:M496,1%))^12-1 -> #VALUE!
B13: celkova zaplatena | C13: =(SUM(B17:B496)*-1)+C6+C8+C9+H17 -> #NUM! | M13: celkova zaplatena | N13: =(SUM(M17:M496)*-1)+N6+N8+N9+S17 -> #DIV/0!
B15: CF | C15: zostatok | M15: CF | N15: zostatok
A16: mesiac | B16: =C3-C6-C7-C9-C11-H17 -> 0 | C16: =C3 -> 0 | D16: istina | E16: urok | F16: splatka | G16: splatka LI | H16: LI nezapoč | L16: mesiac | M16: =N3-N6-N7-N9-S17 -> 0 | N16: =N3 -> 0 | O16: istina | P16: urok | Q16: splatka | R16: splatka LI | S16: LI nezapoč
A17: 1 | B17: =IF(C16>0.00001,F17-G17,0) -> 0 | C17: =MAX(C16-D17,0) -> #NUM! | D17: =(F17-E17)*-1 -> #NUM! | E17: =IPMT($C$4/12,1,$C$5,C16) -> #NUM! | F17: =PMT($C$4/12,$C$5,$C$3) -> #NUM! | H17: ='prijem - EUR-viac-domacnosti'!F121 -> 0 | L17: 1 | M17: =IF(N16>0.00001,Q17-R17,0)*-1 -> 0 | N17: =MAX(N16-O17,0) -> #DIV/0! | O17: =$N$16/$N$5 -> #DIV/0! | P17: =N16*$N$4/12 -> 0 | Q17: =P17+O17 -> #DIV/0! | S17: ='prijem - EUR-viac-domacnosti'!F121 -> 0
A18: 2 | B18: =IF(C17>0.00001,F18-G18,0) -> #NUM! | C18: =MAX(C17-D18,0) -> #NUM! | D18: =(F18-E18)*-1 -> #NUM! | E18: =IPMT($C$4/12,1,$C$5,C17) -> #NUM! | F18: =PMT($C$4/12,$C$5,$C$3) -> #NUM! | L18: 2 | M18: =IF(N17>0.00001,Q18-R18,0)*-1 -> #DIV/0! | N18: =MAX(N17-O18,0) -> #DIV/0! | O18: =$N$16/$N$5 -> #DIV/0! | P18: =N17*$N$4/12 -> #DIV/0! | Q18: =P18+O18 -> #DIV/0!
A19: 3 | B19: =IF(C18>0.00001,F19-G19,0) -> #NUM! | C19: =MAX(C18-D19,0) -> #NUM! | D19: =(F19-E19)*-1 -> #NUM! | E19: =IPMT($C$4/12,1,$C$5,C18) -> #NUM! | F19: =PMT($C$4/12,$C$5,$C$3) -> #NUM! | L19: 3 | M19: =IF(N18>0.00001,Q19-R19,0)*-1 -> #DIV/0! | N19: =MAX(N18-O19,0) -> #DIV/0! | O19: =$N$16/$N$5 -> #DIV/0! | P19: =N18*$N$4/12 -> #DIV/0! | Q19: =P19+O19 -> #DIV/0!
A20: 4 | B20: =IF(C19>0.00001,F20-G20,0) -> #NUM! | C20: =MAX(C19-D20,0) -> #NUM! | D20: =(F20-E20)*-1 -> #NUM! | E20: =IPMT($C$4/12,1,$C$5,C19) -> #NUM! | F20: =PMT($C$4/12,$C$5,$C$3) -> #NUM! | L20: 4 | M20: =IF(N19>0.00001,Q20-R20,0)*-1 -> #DIV/0! | N20: =MAX(N19-O20,0) -> #DIV/0! | O20: =$N$16/$N$5 -> #DIV/0! | P20: =N19*$N$4/12 -> #DIV/0! | Q20: =P20+O20 -> #DIV/0!
A21: 5 | B21: =IF(C20>0.00001,F21-G21,0) -> #NUM! | C21: =MAX(C20-D21,0) -> #NUM! | D21: =(F21-E21)*-1 -> #NUM! | E21: =IPMT($C$4/12,1,$C$5,C20) -> #NUM! | F21: =PMT($C$4/12,$C$5,$C$3) -> #NUM! | L21: 5 | M21: =IF(N20>0.00001,Q21-R21,0)*-1 -> #DIV/0! | N21: =MAX(N20-O21,0) -> #DIV/0! | O21: =$N$16/$N$5 -> #DIV/0! | P21: =N20*$N$4/12 -> #DIV/0! | Q21: =P21+O21 -> #DIV/0!
A22: 6 | B22: =IF(C21>0.00001,F22-G22,0) -> #NUM! | C22: =MAX(C21-D22,0) -> #NUM! | D22: =(F22-E22)*-1 -> #NUM! | E22: =IPMT($C$4/12,1,$C$5,C21) -> #NUM! | F22: =PMT($C$4/12,$C$5,$C$3) -> #NUM! | L22: 6 | M22: =IF(N21>0.00001,Q22-R22,0)*-1 -> #DIV/0! | N22: =MAX(N21-O22,0) -> #DIV/0! | O22: =$N$16/$N$5 -> #DIV/0! | P22: =N21*$N$4/12 -> #DIV/0! | Q22: =P22+O22 -> #DIV/0!
A23: 7 | B23: =IF(C22>0.00001,F23-G23,0) -> #NUM! | C23: =MAX(C22-D23,0) -> #NUM! | D23: =(F23-E23)*-1 -> #NUM! | E23: =IPMT($C$4/12,1,$C$5,C22) -> #NUM! | F23: =PMT($C$4/12,$C$5,$C$3) -> #NUM! | L23: 7 | M23: =IF(N22>0.00001,Q23-R23,0)*-1 -> #DIV/0! | N23: =MAX(N22-O23,0) -> #DIV/0! | O23: =$N$16/$N$5 -> #DIV/0! | P23: =N22*$N$4/12 -> #DIV/0! | Q23: =P23+O23 -> #DIV/0!
A24: 8 | B24: =IF(C23>0.00001,F24-G24,0) -> #NUM! | C24: =MAX(C23-D24,0) -> #NUM! | D24: =(F24-E24)*-1 -> #NUM! | E24: =IPMT($C$4/12,1,$C$5,C23) -> #NUM! | F24: =PMT($C$4/12,$C$5,$C$3) -> #NUM! | L24: 8 | M24: =IF(N23>0.00001,Q24-R24,0)*-1 -> #DIV/0! | N24: =MAX(N23-O24,0) -> #DIV/0! | O24: =$N$16/$N$5 -> #DIV/0! | P24: =N23*$N$4/12 -> #DIV/0! | Q24: =P24+O24 -> #DIV/0!
A25: 9 | B25: =IF(C24>0.00001,F25-G25,0) -> #NUM! | C25: =MAX(C24-D25,0) -> #NUM! | D25: =(F25-E25)*-1 -> #NUM! | E25: =IPMT($C$4/12,1,$C$5,C24) -> #NUM! | F25: =PMT($C$4/12,$C$5,$C$3) -> #NUM! | L25: 9 | M25: =IF(N24>0.00001,Q25-R25,0)*-1 -> #DIV/0! | N25: =MAX(N24-O25,0) -> #DIV/0! | O25: =$N$16/$N$5 -> #DIV/0! | P25: =N24*$N$4/12 -> #DIV/0! | Q25: =P25+O25 -> #DIV/0!
A26: 10 | B26: =IF(C25>0.00001,F26-G26,0) -> #NUM! | C26: =MAX(C25-D26,0) -> #NUM! | D26: =(F26-E26)*-1 -> #NUM! | E26: =IPMT($C$4/12,1,$C$5,C25) -> #NUM! | F26: =PMT($C$4/12,$C$5,$C$3) -> #NUM! | L26: 10 | M26: =IF(N25>0.00001,Q26-R26,0)*-1 -> #DIV/0! | N26: =MAX(N25-O26,0) -> #DIV/0! | O26: =$N$16/$N$5 -> #DIV/0! | P26: =N25*$N$4/12 -> #DIV/0! | Q26: =P26+O26 -> #DIV/0!
A27: 11 | B27: =IF(C26>0.00001,F27-G27,0) -> #NUM! | C27: =MAX(C26-D27,0) -> #NUM! | D27: =(F27-E27)*-1 -> #NUM! | E27: =IPMT($C$4/12,1,$C$5,C26) -> #NUM! | F27: =PMT($C$4/12,$C$5,$C$3) -> #NUM! | L27: 11 | M27: =IF(N26>0.00001,Q27-R27,0)*-1 -> #DIV/0! | N27: =MAX(N26-O27,0) -> #DIV/0! | O27: =$N$16/$N$5 -> #DIV/0! | P27: =N26*$N$4/12 -> #DIV/0! | Q27: =P27+O27 -> #DIV/0!
A28: 12 | B28: =IF(C27>0.00001,F28-G28,0) -> #NUM! | C28: =MAX(C27-D28,0) -> #NUM! | D28: =(F28-E28)*-1 -> #NUM! | E28: =IPMT($C$4/12,1,$C$5,C27) -> #NUM! | F28: =PMT($C$4/12,$C$5,$C$3) -> #NUM! | L28: 12 | M28: =IF(N27>0.00001,Q28-R28,0)*-1 -> #DIV/0! | N28: =MAX(N27-O28,0) -> #DIV/0! | O28: =$N$16/$N$5 -> #DIV/0! | P28: =N27*$N$4/12 -> #DIV/0! | Q28: =P28+O28 -> #DIV/0!
A29: 13 | B29: =IF(C28>0.00001,F29-G29,0) -> #NUM! | C29: =MAX(C28-D29,0) -> #NUM! | D29: =(F29-E29)*-1 -> #NUM! | E29: =IPMT($C$4/12,1,$C$5,C28) -> #NUM! | F29: =PMT($C$4/12,$C$5,$C$3) -> #NUM! | L29: 13 | M29: =IF(N28>0.00001,Q29-R29,0)*-1 -> #DIV/0! | N29: =MAX(N28-O29,0) -> #DIV/0! | O29: =$N$16/$N$5 -> #DIV/0! | P29: =N28*$N$4/12 -> #DIV/0! | Q29: =P29+O29 -> #DIV/0!
... A40: 24 | B40: =IF(C39>0.00001,F40-G40,0) -> #NUM! | C40: =MAX(C39-D40,0) -> #NUM! | D40: =(F40-E40)*-1 -> #NUM! | E40: =IPMT($C$4/12,1,$C$5,C39) -> #NUM! | F40: =PMT($C$4/12,$C$5,$C$3) -> #NUM! | L40: 24 | M40: =IF(N39>0.00001,Q40-R40,0)*-1 -> #DIV/0! | N40: =MAX(N39-O40,0) -> #DIV/0! | O40: =$N$16/$N$5 -> #DIV/0! | P40: =N39*$N$4/12 -> #DIV/0! | Q40: =P40+O40 -> #DIV/0!
A41: 25 | B41: =IF(C40>0.00001,F41-G41,0) -> #NUM! | C41: =MAX(C40-D41,0) -> #NUM! | D41: =(F41-E41)*-1 -> #NUM! | E41: =IPMT($C$4/12,1,$C$5,C40) -> #NUM! | F41: =PMT($C$4/12,$C$5,$C$3) -> #NUM! | G41: =IF('prijem - EUR-viac-domacnosti'!$I$120=TRUE,IF($C$11>0,0.00025*C40,0),IF('prijem - EUR-viac-domacnosti'!$I$121=TRUE,IF('prijem - EUR-viac-domacnosti'!$F$121>0,0.00025*C40,0),0)) -> 0 | L41: 25 | M41: =IF(N40>0.00001,Q41-R41,0)*-1 -> #DIV/0! | N41: =MAX(N40-O41,0) -> #DIV/0! | O41: =$N$16/$N$5 -> #DIV/0! | P41: =N40*$N$4/12 -> #DIV/0! | Q41: =P41+O41 -> #DIV/0! | R41: =IF('prijem - EUR-viac-domacnosti'!$I$120=TRUE,IF($C$11>0,0.00025*N40,0),IF('prijem - EUR-viac-domacnosti'!$I$121=TRUE,IF('prijem - EUR-viac-domacnosti'!$F$121>0,0.00025*N40*-1,0),0)) -> 0
A42: 26 | B42: =IF(C41>0.00001,F42-G42,0) -> #NUM! | C42: =MAX(C41-D42,0) -> #NUM! | D42: =(F42-E42)*-1 -> #NUM! | E42: =IPMT($C$4/12,1,$C$5,C41) -> #NUM! | F42: =PMT($C$4/12,$C$5,$C$3) -> #NUM! | G42: =IF('prijem - EUR-viac-domacnosti'!$I$120=TRUE,IF($C$11>0,0.00025*C41,0),IF('prijem - EUR-viac-domacnosti'!$I$121=TRUE,IF('prijem - EUR-viac-domacnosti'!$F$121>0,0.00025*C41,0),0)) -> 0 | L42: 26 | M42: =IF(N41>0.00001,Q42-R42,0)*-1 -> #DIV/0! | N42: =MAX(N41-O42,0) -> #DIV/0! | O42: =$N$16/$N$5 -> #DIV/0! | P42: =N41*$N$4/12 -> #DIV/0! | Q42: =P42+O42 -> #DIV/0! | R42: =IF('prijem - EUR-viac-domacnosti'!$I$120=TRUE,IF($C$11>0,0.00025*N41,0),IF('prijem - EUR-viac-domacnosti'!$I$121=TRUE,IF('prijem - EUR-viac-domacnosti'!$F$121>0,0.00025*N41*-1,0),0)) -> 0
A43: 27 | B43: =IF(C42>0.00001,F43-G43,0) -> #NUM! | C43: =MAX(C42-D43,0) -> #NUM! | D43: =(F43-E43)*-1 -> #NUM! | E43: =IPMT($C$4/12,1,$C$5,C42) -> #NUM! | F43: =PMT($C$4/12,$C$5,$C$3) -> #NUM! | G43: =IF('prijem - EUR-viac-domacnosti'!$I$120=TRUE,IF($C$11>0,0.00025*C42,0),IF('prijem - EUR-viac-domacnosti'!$I$121=TRUE,IF('prijem - EUR-viac-domacnosti'!$F$121>0,0.00025*C42,0),0)) -> 0 | L43: 27 | M43: =IF(N42>0.00001,Q43-R43,0)*-1 -> #DIV/0! | N43: =MAX(N42-O43,0) -> #DIV/0! | O43: =$N$16/$N$5 -> #DIV/0! | P43: =N42*$N$4/12 -> #DIV/0! | Q43: =P43+O43 -> #DIV/0! | R43: =IF('prijem - EUR-viac-domacnosti'!$I$120=TRUE,IF($C$11>0,0.00025*N42,0),IF('prijem - EUR-viac-domacnosti'!$I$121=TRUE,IF('prijem - EUR-viac-domacnosti'!$F$121>0,0.00025*N42*-1,0),0)) -> 0
A44: 28 | B44: =IF(C43>0.00001,F44-G44,0) -> #NUM! | C44: =MAX(C43-D44,0) -> #NUM! | D44: =(F44-E44)*-1 -> #NUM! | E44: =IPMT($C$4/12,1,$C$5,C43) -> #NUM! | F44: =PMT($C$4/12,$C$5,$C$3) -> #NUM! | G44: =IF('prijem - EUR-viac-domacnosti'!$I$120=TRUE,IF($C$11>0,0.00025*C43,0),IF('prijem - EUR-viac-domacnosti'!$I$121=TRUE,IF('prijem - EUR-viac-domacnosti'!$F$121>0,0.00025*C43,0),0)) -> 0 | L44: 28 | M44: =IF(N43>0.00001,Q44-R44,0)*-1 -> #DIV/0! | N44: =MAX(N43-O44,0) -> #DIV/0! | O44: =$N$16/$N$5 -> #DIV/0! | P44: =N43*$N$4/12 -> #DIV/0! | Q44: =P44+O44 -> #DIV/0! | R44: =IF('prijem - EUR-viac-domacnosti'!$I$120=TRUE,IF($C$11>0,0.00025*N43,0),IF('prijem - EUR-viac-domacnosti'!$I$121=TRUE,IF('prijem - EUR-viac-domacnosti'!$F$121>0,0.00025*N43*-1,0),0)) -> 0
A45: 29 | B45: =IF(C44>0.00001,F45-G45,0) -> #NUM! | C45: =MAX(C44-D45,0) -> #NUM! | D45: =(F45-E45)*-1 -> #NUM! | E45: =IPMT($C$4/12,1,$C$5,C44) -> #NUM! | F45: =PMT($C$4/12,$C$5,$C$3) -> #NUM! | G45: =IF('prijem - EUR-viac-domacnosti'!$I$120=TRUE,IF($C$11>0,0.00025*C44,0),IF('prijem - EUR-viac-domacnosti'!$I$121=TRUE,IF('prijem - EUR-viac-domacnosti'!$F$121>0,0.00025*C44,0),0)) -> 0 | L45: 29 | M45: =IF(N44>0.00001,Q45-R45,0)*-1 -> #DIV/0! | N45: =MAX(N44-O45,0) -> #DIV/0! | O45: =$N$16/$N$5 -> #DIV/0! | P45: =N44*$N$4/12 -> #DIV/0! | Q45: =P45+O45 -> #DIV/0! | R45: =IF('prijem - EUR-viac-domacnosti'!$I$120=TRUE,IF($C$11>0,0.00025*N44,0),IF('prijem - EUR-viac-domacnosti'!$I$121=TRUE,IF('prijem - EUR-viac-domacnosti'!$F$121>0,0.00025*N44*-1,0),0)) -> 0
A46: 30 | B46: =IF(C45>0.00001,F46-G46,0) -> #NUM! | C46: =MAX(C45-D46,0) -> #NUM! | D46: =(F46-E46)*-1 -> #NUM! | E46: =IPMT($C$4/12,1,$C$5,C45) -> #NUM! | F46: =PMT($C$4/12,$C$5,$C$3) -> #NUM! | G46: =IF('prijem - EUR-viac-domacnosti'!$I$120=TRUE,IF($C$11>0,0.00025*C45,0),IF('prijem - EUR-viac-domacnosti'!$I$121=TRUE,IF('prijem - EUR-viac-domacnosti'!$F$121>0,0.00025*C45,0),0)) -> 0 | L46: 30 | M46: =IF(N45>0.00001,Q46-R46,0)*-1 -> #DIV/0! | N46: =MAX(N45-O46,0) -> #DIV/0! | O46: =$N$16/$N$5 -> #DIV/0! | P46: =N45*$N$4/12 -> #DIV/0! | Q46: =P46+O46 -> #DIV/0! | R46: =IF('prijem - EUR-viac-domacnosti'!$I$120=TRUE,IF($C$11>0,0.00025*N45,0),IF('prijem - EUR-viac-domacnosti'!$I$121=TRUE,IF('prijem - EUR-viac-domacnosti'!$F$121>0,0.00025*N45*-1,0),0)) -> 0
A47: 31 | B47: =IF(C46>0.00001,F47-G47,0) -> #NUM! | C47: =MAX(C46-D47,0) -> #NUM! | D47: =(F47-E47)*-1 -> #NUM! | E47: =IPMT($C$4/12,1,$C$5,C46) -> #NUM! | F47: =PMT($C$4/12,$C$5,$C$3) -> #NUM! | G47: =IF('prijem - EUR-viac-domacnosti'!$I$120=TRUE,IF($C$11>0,0.00025*C46,0),IF('prijem - EUR-viac-domacnosti'!$I$121=TRUE,IF('prijem - EUR-viac-domacnosti'!$F$121>0,0.00025*C46,0),0)) -> 0 | L47: 31 | M47: =IF(N46>0.00001,Q47-R47,0)*-1 -> #DIV/0! | N47: =MAX(N46-O47,0) -> #DIV/0! | O47: =$N$16/$N$5 -> #DIV/0! | P47: =N46*$N$4/12 -> #DIV/0! | Q47: =P47+O47 -> #DIV/0! | R47: =IF('prijem - EUR-viac-domacnosti'!$I$120=TRUE,IF($C$11>0,0.00025*N46,0),IF('prijem - EUR-viac-domacnosti'!$I$121=TRUE,IF('prijem - EUR-viac-domacnosti'!$F$121>0,0.00025*N46*-1,0),0)) -> 0
A48: 32 | B48: =IF(C47>0.00001,F48-G48,0) -> #NUM! | C48: =MAX(C47-D48,0) -> #NUM! | D48: =(F48-E48)*-1 -> #NUM! | E48: =IPMT($C$4/12,1,$C$5,C47) -> #NUM! | F48: =PMT($C$4/12,$C$5,$C$3) -> #NUM! | G48: =IF('prijem - EUR-viac-domacnosti'!$I$120=TRUE,IF($C$11>0,0.00025*C47,0),IF('prijem - EUR-viac-domacnosti'!$I$121=TRUE,IF('prijem - EUR-viac-domacnosti'!$F$121>0,0.00025*C47,0),0)) -> 0 | L48: 32 | M48: =IF(N47>0.00001,Q48-R48,0)*-1 -> #DIV/0! | N48: =MAX(N47-O48,0) -> #DIV/0! | O48: =$N$16/$N$5 -> #DIV/0! | P48: =N47*$N$4/12 -> #DIV/0! | Q48: =P48+O48 -> #DIV/0! | R48: =IF('prijem - EUR-viac-domacnosti'!$I$120=TRUE,IF($C$11>0,0.00025*N47,0),IF('prijem - EUR-viac-domacnosti'!$I$121=TRUE,IF('prijem - EUR-viac-domacnosti'!$F$121>0,0.00025*N47*-1,0),0)) -> 0
A49: 33 | B49: =IF(C48>0.00001,F49-G49,0) -> #NUM! | C49: =MAX(C48-D49,0) -> #NUM! | D49: =(F49-E49)*-1 -> #NUM! | E49: =IPMT($C$4/12,1,$C$5,C48) -> #NUM! | F49: =PMT($C$4/12,$C$5,$C$3) -> #NUM! | G49: =IF('prijem - EUR-viac-domacnosti'!$I$120=TRUE,IF($C$11>0,0.00025*C48,0),IF('prijem - EUR-viac-domacnosti'!$I$121=TRUE,IF('prijem - EUR-viac-domacnosti'!$F$121>0,0.00025*C48,0),0)) -> 0 | L49: 33 | M49: =IF(N48>0.00001,Q49-R49,0)*-1 -> #DIV/0! | N49: =MAX(N48-O49,0) -> #DIV/0! | O49: =$N$16/$N$5 -> #DIV/0! | P49: =N48*$N$4/12 -> #DIV/0! | Q49: =P49+O49 -> #DIV/0! | R49: =IF('prijem - EUR-viac-domacnosti'!$I$120=TRUE,IF($C$11>0,0.00025*N48,0),IF('prijem - EUR-viac-domacnosti'!$I$121=TRUE,IF('prijem - EUR-viac-domacnosti'!$F$121>0,0.00025*N48*-1,0),0)) -> 0
A50: 34 | B50: =IF(C49>0.00001,F50-G50,0) -> #NUM! | C50: =MAX(C49-D50,0) -> #NUM! | D50: =(F50-E50)*-1 -> #NUM! | E50: =IPMT($C$4/12,1,$C$5,C49) -> #NUM! | F50: =PMT($C$4/12,$C$5,$C$3) -> #NUM! | G50: =IF('prijem - EUR-viac-domacnosti'!$I$120=TRUE,IF($C$11>0,0.00025*C49,0),IF('prijem - EUR-viac-domacnosti'!$I$121=TRUE,IF('prijem - EUR-viac-domacnosti'!$F$121>0,0.00025*C49,0),0)) -> 0 | L50: 34 | M50: =IF(N49>0.00001,Q50-R50,0)*-1 -> #DIV/0! | N50: =MAX(N49-O50,0) -> #DIV/0! | O50: =$N$16/$N$5 -> #DIV/0! | P50: =N49*$N$4/12 -> #DIV/0! | Q50: =P50+O50 -> #DIV/0! | R50: =IF('prijem - EUR-viac-domacnosti'!$I$120=TRUE,IF($C$11>0,0.00025*N49,0),IF('prijem - EUR-viac-domacnosti'!$I$121=TRUE,IF('prijem - EUR-viac-domacnosti'!$F$121>0,0.00025*N49*-1,0),0)) -> 0
A51: 35 | B51: =IF(C50>0.00001,F51-G51,0) -> #NUM! | C51: =MAX(C50-D51,0) -> #NUM! | D51: =(F51-E51)*-1 -> #NUM! | E51: =IPMT($C$4/12,1,$C$5,C50) -> #NUM! | F51: =PMT($C$4/12,$C$5,$C$3) -> #NUM! | G51: =IF('prijem - EUR-viac-domacnosti'!$I$120=TRUE,IF($C$11>0,0.00025*C50,0),IF('prijem - EUR-viac-domacnosti'!$I$121=TRUE,IF('prijem - EUR-viac-domacnosti'!$F$121>0,0.00025*C50,0),0)) -> 0 | L51: 35 | M51: =IF(N50>0.00001,Q51-R51,0)*-1 -> #DIV/0! | N51: =MAX(N50-O51,0) -> #DIV/0! | O51: =$N$16/$N$5 -> #DIV/0! | P51: =N50*$N$4/12 -> #DIV/0! | Q51: =P51+O51 -> #DIV/0! | R51: =IF('prijem - EUR-viac-domacnosti'!$I$120=TRUE,IF($C$11>0,0.00025*N50,0),IF('prijem - EUR-viac-domacnosti'!$I$121=TRUE,IF('prijem - EUR-viac-domacnosti'!$F$121>0,0.00025*N50*-1,0),0)) -> 0
A52: 36 | B52: =IF(C51>0.00001,F52-G52,0) -> #NUM! | C52: =MAX(C51-D52,0) -> #NUM! | D52: =(F52-E52)*-1 -> #NUM! | E52: =IPMT($C$4/12,1,$C$5,C51) -> #NUM! | F52: =PMT($C$4/12,$C$5,$C$3) -> #NUM! | G52: =IF('prijem - EUR-viac-domacnosti'!$I$120=TRUE,IF($C$11>0,0.00025*C51,0),IF('prijem - EUR-viac-domacnosti'!$I$121=TRUE,IF('prijem - EUR-viac-domacnosti'!$F$121>0,0.00025*C51,0),0)) -> 0 | L52: 36 | M52: =IF(N51>0.00001,Q52-R52,0)*-1 -> #DIV/0! | N52: =MAX(N51-O52,0) -> #DIV/0! | O52: =$N$16/$N$5 -> #DIV/0! | P52: =N51*$N$4/12 -> #DIV/0! | Q52: =P52+O52 -> #DIV/0! | R52: =IF('prijem - EUR-viac-domacnosti'!$I$120=TRUE,IF($C$11>0,0.00025*N51,0),IF('prijem - EUR-viac-domacnosti'!$I$121=TRUE,IF('prijem - EUR-viac-domacnosti'!$F$121>0,0.00025*N51*-1,0),0)) -> 0
... A496: 480 | B496: =IF(C495>0.00001,F496-G496,0) -> #NUM! | C496: =MAX(C495-D496,0) -> #NUM! | D496: =(F496-E496)*-1 -> #NUM! | E496: =IPMT($C$4/12,1,$C$5,C495) -> #NUM! | F496: =PMT($C$4/12,$C$5,$C$3) -> #NUM! | G496: =IF('prijem - EUR-viac-domacnosti'!$I$120=TRUE,IF($C$11>0,0.00025*C495,0),IF('prijem - EUR-viac-domacnosti'!$I$121=TRUE,IF('prijem - EUR-viac-domacnosti'!$F$121>0,0.00025*C495,0),0)) -> 0 | L496: 480 | M496: =IF(N495>0.00001,Q496-R496,0)*-1 -> #DIV/0! | N496: =MAX(N495-O496,0) -> #DIV/0! | O496: =$N$16/$N$5 -> #DIV/0! | P496: =N495*$N$4/12 -> #DIV/0! | Q496: =P496+O496 -> #DIV/0! | R496: =IF('prijem - EUR-viac-domacnosti'!$I$120=TRUE,IF($C$11>0,0.00025*N495,0),IF('prijem - EUR-viac-domacnosti'!$I$121=TRUE,IF('prijem - EUR-viac-domacnosti'!$F$121>0,0.00025*N495*-1,0),0)) -> 0
A497: 481 | L497: 481

Sheet prijem_zahranicie - viac-dom
C1: Kalkulačka mHypotéka
D3: Jméno klienta
F4: =IF(ISBLANK(F3),"DÁTUM PODANIA!","OK") -> DÁTUM PODANIA!
D5: Číslo žádosti
D7: Mesačný čistý príjem domácnosti v EUR (prepočtený dle veku) No.1 | F7: =F9+F11+F12+F14+F15+F17 -> 0
D8: Mesačný čistý príjem domácnosti v EUR (neprepočtený dle veku) No.1 | F8: =F10+F11+F13+F14+F16+F17 -> 0
D9: Čistý príjem žiadateľa č.1 zo závislej činnosti alebo živnosti | F9: =IF(F21="","0",(F10*(F86-MIN(MAX(F21+F86-744,0),F86))/F86)+(F10*0.85*MIN(MAX(F21+F86-744,0),F86)/F86)) -> 0
D10: Čistý príjem žiadateľa č.1 zo závislej činnosti alebo živnosti
D11: Čistý príjem žiadateľa č.1 z inej činnosti
D12: Čistý príjem žiadateľa č.2 zo závislej činnosti alebo živnosti | F12: =IF(F24="","0",(F13*(F86-MIN(MAX(F24+F86-744,0),F86))/F86)+(F13*0.85*MIN(MAX(F24+F86-744,0),F86)/F86)) -> 0
D13: Čistý príjem žiadateľa č.2 zo závislej činnosti alebo živnosti
D14: Čistý príjem žiadateľa č.2 z inej činnosti
D15: Čistý príjem žiadateľa č.3 zo závislej činnosti alebo živnosti | F15: =IF(F27="","0",(F16*(F86-MIN(MAX(F27+F86-744,0),F86))/F86)+(F16*0.85*MIN(MAX(F27+F86-744,0),F86)/F86)) -> 0
D16: Čistý príjem žiadateľa č.3 zo závislej činnosti alebo živnosti
D17: Čistý príjem žiadateľa č.3 z inej činnosti
D18: Počet žiadatelov
D19: Dátum narodenia žiadateľa č.1
D20: Vek žiadateľa č.1 na limity | F20: =IF(F19="","",YEAR(F3)-YEAR(F19))
D21: Vek žiadateľa č.1 v mesiacoch | F21: =IF(F19="","",(DATEDIF(F19,F3,"M"))+(IF((DAY(F19)-DAY(F3))<=0,0,1)))
D22: Dátum narodenia žiadateľa č. 2
D23: Vek žiadateľa č.2 na limity | F23: =IF(F22="","",YEAR(F3)-YEAR(F22))
D24: Vek žiadateľa č.2 v mesiacoch | F24: =IF(F22="","",(DATEDIF(F22,F3,"M"))+(IF((DAY(F22)-DAY(F3))<=0,0,1)))
D25: Dátum narodenia žiadateľa č. 3
D26: Vek žiadateľa č.3 na limity | F26: =IF(F25="","",YEAR(F3)-YEAR(F25))
D27: Vek žiadateľa č.3 v mesiacoch | F27: =IF(F25="","",(DATEDIF(F25,F3,"M"))+(IF((DAY(F25)-DAY(F3))<=0,0,1)))
D28: Počet žiadatelmi vyživovaných osôb | F28: 0
D29: Number of dependants with applicants | F29: =$F$18+$F$28 -> 0
D30: v tom detí | F30: 0
D31: Available income (including household expenses) | F31: =MAX(0.95*(F7-MAX($F$32,$F$33)),0) -> 0
D32: Expenses - according to Slovak law (COSTS) | F32: =IF($F$29=0,0,0.2*(F7-(210.2+($F$29-$F$30-1)*146.64+($F$30)*95.96+$F$40))+(210.2+($F$29-$F$30-1)*146.64+($F$30)*95.96+$F$40)) -> 0
D33: Expenses - according to the Bank's model (KUGD) | F33: =IF($F$29=0,0,MAX($F$29*((185*($F$29^(-0.4)))^(1-0.4))*(($F$8/$F$29)^(0.4)),0)) -> 0
D35: Výška mesačných splátok splátkových úverov v mBank | F35: 0
D36: Výška mesačných splátok splátkových úverov v iných bankách | F36: 0
D37: Limity kontokorentných úverov | F37: 0
D38: Limity kreditných kariet | F38: 0
D39: Výška mesačných splátok alimentov, exekúcií a iných záväzkov | F39: 0
D40: Prepočtená výška mesačných splátok alimentov, exekúcií a iných záväzkov | F40: =IF($F$39=0,0,IF($F$39>30,$F$39,30)) -> 0
D41: Free income (including liabilities) | F41: =MAX((MIN($F$31,0.75*F7)-$F$35-($F$36*1.2)-0.03*$F$37-0.03*$F$38),0) -> 0
D45: Mesačný čistý príjem domácnosti v EUR (prepočtený dle veku) No.2 | F45: =F47+F49+F50+F52+F53+F55 -> 0
D46: Mesačný čistý príjem domácnosti v EUR (neprepočtený dle veku) No.2 | F46: =F48+F49+F51+F52+F54+F55 -> 0
D47: Čistý príjem žiadateľa č.1 zo závislej činnosti alebo živnosti | F47: =IF(F59="","0",(F48*(F86-MIN(MAX(F59+F86-744,0),F86))/F86)+(F48*0.85*MIN(MAX(F59+F86-744,0),F86)/F86)) -> 0
D48: Čistý príjem žiadateľa č.1 zo závislej činnosti alebo živnosti
D49: Čistý príjem žiadateľa č.1 z inej činnosti
D50: Čistý príjem žiadateľa č.2 zo závislej činnosti alebo živnosti | F50: =IF(F62="","0",(F51*(F86-MIN(MAX(F62+F86-744,0),F86))/F86)+(F51*0.85*MIN(MAX(F62+F86-744,0),F86)/F86)) -> 0
D51: Čistý príjem žiadateľa č.2 zo závislej činnosti alebo živnosti
D52: Čistý príjem žiadateľa č.2 z inej činnosti
D53: Čistý príjem žiadateľa č.3 zo závislej činnosti alebo živnosti | F53: =IF(F65="","0",(F54*(F86-MIN(MAX(F65+F86-744,0),F86))/F86)+(F54*0.85*MIN(MAX(F65+F86-744,0),F86)/F86)) -> 0
D54: Čistý príjem žiadateľa č.3 zo závislej činnosti alebo živnosti
D55: Čistý príjem žiadateľa č.3 z inej činnosti
D56: Počet žiadatelov | F56: 0
D57: Dátum narodenia žiadateľa č. 1
D58: Vek žiadateľa č.1 na limity | F58: =IF(F57="","",YEAR(F3)-YEAR(F57))
D59: Vek žiadateľa č.1 v mesiacoch | F59: =IF(F57="","",(DATEDIF(F57,F3,"M"))+(IF((DAY(F57)-DAY(F3))<=0,0,1)))
D60: Dátum narodenia žiadateľa č. 2
D61: Vek žiadateľa č.2 na limity | F61: =IF(F60="","",YEAR(F3)-YEAR(F60))
D62: Vek žiadateľa č.2 v mesiacoch | F62: =IF(F60="","",(DATEDIF(F60,F3,"M"))+(IF((DAY(F60)-DAY(F3))<=0,0,1)))
D63: Dátum narodenia žiadateľa č. 3
D64: Vek žiadateľa č.3 na limity | F64: =IF(F63="","",YEAR(F3)-YEAR(F63))
D65: Vek žiadateľa č.3 v mesiacoch | F65: =IF(F63="","",(DATEDIF(F63,F3,"M"))+(IF((DAY(F63)-DAY(F3))<=0,0,1)))
D66: Počet žiadatelmi vyživovaných osôb | F66: 0
D67: Number of dependants with applicants | F67: =$F$56+$F$66 -> 0
D68: v tom detí | F68: 0
D69: Available income (including household expenses) | F69: =MAX(0.95*(F45-MAX($F$70,$F$71)),0) -> 0
D70: Expenses - according to Slovak law (COSTS) | F70: =IF($F$67=0,0,0.2*(F45-(210.2+($F$67-$F$68-1)*146.64+($F$68)*95.96+$F$78))+(210.2+($F$67-$F$68-1)*146.64+($F$68)*95.96+$F$78)) -> 0
D71: Expenses - according to the Bank's model (KUGD) | F71: =IF($F$67=0,0,MAX($F$67*((185*($F$67^(-0.4)))^(1-0.4))*(($F$46/$F$67)^(0.4)),0)) -> 0
D73: Výška mesačných splátok splátkových úverov v mBank | F73: 0
D74: Výška mesačných splátok splátkových úverov v iných bankách | F74: 0
D75: Limity kontokorentných úverov | F75: 0
D76: Limity kreditných kariet | F76: 0
D77: Výška mesačných splátok alimentov, exekúcií a iných záväzkov | F77: 0
D78: Prepočtená výška mesačných splátok alimentov, exekúcií a iných záväzkov | F78: =IF($F$77=0,0,IF($F$77>30,$F$77,30)) -> 0
D79: Free income (including liabilities) | F79: =MAX((MIN($F$69,0.75*F45)-$F$73-($F$74*1.2)-0.03*$F$75-0.03*$F$76),0) -> 0
D80: Free income for both households (including liabilities) | F80: =F41+F79 -> 0
D84: Žiadaná čiastka úveru v EUR
D85: Žiadaná čiastka úveru s Life Insurance | F85: =F84+F121 -> 0
D86: Žiadaná doba splátkoveho úveru (v mesiacoch)
D87: Hodnota nehnuteľ. ponúkanej ako zabezpečenie úveru v EUR č.1
D88: Volná hodnota nehnuteľnosti č.1
D89: Cena ZP č. 1
D90: Poistné č. 1 ročné
D91: Poistné č. 1 za dobu splácania | F91: =(F90/12)*F86 -> 0
D92: Štandardná hodnota ukazovateľa LtV (% | F92: 0.8
D93: Maximálna hodnota ukazovateľa LtV (%) | F93: =IF(F92=80%,100%,IF(F92=70%,"80%",IF(C132=2,"75%","90%"))) -> 1
D94: Hodnota nehnuteľ. ponúkanej ako zabezpečenie úveru v EUR č.2
D95: Volná hodnota nehnuteľnosti č.2
D96: Cena ZP č. 2
D97: Poistné č. 2 ročné
D98: Poistné č. 2 za celú dobu splácania | F98: =(F97/12)*F86 -> 0
D99: Štandardná hodnota ukazovateľa LtV (%) | F99: 0.7
D100: Maximálna hodnota ukazovateľa LtV (%) | F100: =IF(F99=80%,100%,IF(F99=70%,"80%",IF(C132=2,"75%","90%"))) -> 80%
D101: Hodnota nehnuteľ. ponúkanej ako zabezpečenie úveru v EUR č.3
D102: Volná hodnota nehnuteľnosti č.3
D103: Cena ZP č. 3
D104: Poistné č. 3 ročné
D105: Poistné č. 3 za celú dobu splácania | F105: =(F104/12)*F86 -> 0
D106: Štandardná hodnota ukazovateľa LtV (%) | F106: 0.65
D107: Maximálna hodnota ukazovateľa LtV (%) | F107: =IF(F106=80%,100%,IF(F106=70%,"80%",IF(C132=2,"75%","90%"))) -> 90%
D108: Skutočná hodnota ukazovateľa LtV (%) | F108: =IFERROR(IF(ISBLANK($F$88)=TRUE,IF(ISBLANK($F$92)=TRUE,0,(F85/(F87+F94+F101))),(F87-F88+F94-F95+F101-F102+F85/(F87+F94+F101))),0) -> 0
D109: Ročná úroková sadzba (%)
D110: Účelový / Neúčelový úver
...

Sheet RPMN - prijem_zah- EUR-vice-dom
A2: anuita | L2: klesajuce
B3: vyska uveru | C3: ='prijem_zahranicie - viac-dom'!F85 -> 0 | M3: vyska uveru | N3: ='prijem_zahranicie - viac-dom'!F85 -> 0
B4: sadzba | C4: ='prijem_zahranicie - viac-dom'!F109 -> 0 | M4: sadzba | N4: ='prijem_zahranicie - viac-dom'!F109 -> 0
B5: splatnost | C5: ='prijem_zahranicie - viac-dom'!F86 -> 0 | M5: splatnost | N5: ='prijem_zahranicie - viac-dom'!F86 -> 0
B6: cena ZP | C6: ='prijem_zahranicie - viac-dom'!F89+'prijem_zahranicie - viac-dom'!F96+'prijem_zahranicie - viac-dom'!F103 -> 0 | M6: cena ZP | N6: ='prijem_zahranicie - viac-dom'!F89+'prijem_zahranicie - viac-dom'!F96+'prijem_zahranicie - viac-dom'!F103 -> 0
B7: poistné za rok | C7: ='prijem_zahranicie - viac-dom'!F90+'prijem_zahranicie - viac-dom'!F97+'prijem_zahranicie - viac-dom'!F104 -> 0 | M7: poistné za rok | N7: ='prijem_zahranicie - viac-dom'!F90+'prijem_zahranicie - viac-dom'!F97+'prijem_zahranicie - viac-dom'!F104 -> 0
B8: poistné za celú dobu | C8: ='prijem_zahranicie - viac-dom'!F91+'prijem_zahranicie - viac-dom'!F98+'prijem_zahranicie - viac-dom'!F105 -> 0 | M8: poistné za celú dobu | N8: ='prijem_zahranicie - viac-dom'!F91+'prijem_zahranicie - viac-dom'!F98+'prijem_zahranicie - viac-dom'!F105 -> 0
B9: vklad do katastru | C9: ='prijem_zahranicie - viac-dom'!E138+'prijem_zahranicie - viac-dom'!E139+'prijem_zahranicie - viac-dom'!E140 -> 0 | M9: vklad do katastru | N9: ='prijem_zahranicie - viac-dom'!E138+'prijem_zahranicie - viac-dom'!E139+'prijem_zahranicie - viac-dom'!E140 -> 0
B10: LCI | C10: #REF! | M10: LCI | N10: #REF!
B11: Life | C11: ='prijem_zahranicie - viac-dom'!F121 -> 0 | M11: Life | N11: ='prijem_zahranicie - viac-dom'!F121 -> 0
B12: RPMN | C12: =(1+IRR(B16:B496,1%))^12-1 -> #VALUE! | M12: RPMN | N12: =(1+IRR(M16:M496,1%))^12-1 -> #VALUE!
B13: celkova zaplatena | C13: =(SUM(B17:B496)*-1)+C6+C8+C9+H17 -> #NUM! | M13: celkova zaplatena | N13: =(SUM(M17:M496)*-1)+N6+N8+N9+S17 -> #DIV/0!
B15: CF | C15: zostatok | M15: CF | N15: zostatok
A16: mesiac | B16: =C3-C6-C7-C9-C11-H17 -> 0 | C16: =C3 -> 0 | D16: istina | E16: urok | F16: splatka | G16: splatka LI | H16: LI nezapoč | L16: mesiac | M16: =N3-N6-N7-N9-N11-S17 -> 0 | N16: =N3 -> 0 | O16: istina | P16: urok | Q16: splatka | R16: splatka LI | S16: LI nezapoč
A17: 1 | B17: =IF(C16>0.00001,F17-G17,0) -> 0 | C17: =MAX(C16-D17,0) -> #NUM! | D17: =(F17-E17)*-1 -> #NUM! | E17: =IPMT($C$4/12,1,$C$5,C16) -> #NUM! | F17: =PMT($C$4/12,$C$5,$C$3) -> #NUM! | H17: ='prijem_zahranicie - viac-dom'!F122 -> 0 | L17: 1 | M17: =IF(N16>0.00001,Q17-R17,0)*-1 -> 0 | N17: =MAX(N16-O17,0) -> #DIV/0! | O17: =$N$16/$N$5 -> #DIV/0! | P17: =N16*$N$4/12 -> 0 | Q17: =P17+O17 -> #DIV/0! | S17: ='prijem_zahranicie - viac-dom'!F122 -> 0
A18: 2 | B18: =IF(C17>0.00001,F18-G18,0) -> #NUM! | C18: =MAX(C17-D18,0) -> #NUM! | D18: =(F18-E18)*-1 -> #NUM! | E18: =IPMT($C$4/12,1,$C$5,C17) -> #NUM! | F18: =PMT($C$4/12,$C$5,$C$3) -> #NUM! | L18: 2 | M18: =IF(N17>0.00001,Q18-R18,0)*-1 -> #DIV/0! | N18: =MAX(N17-O18,0) -> #DIV/0! | O18: =$N$16/$N$5 -> #DIV/0! | P18: =N17*$N$4/12 -> #DIV/0! | Q18: =P18+O18 -> #DIV/0!
A19: 3 | B19: =IF(C18>0.00001,F19-G19,0) -> #NUM! | C19: =MAX(C18-D19,0) -> #NUM! | D19: =(F19-E19)*-1 -> #NUM! | E19: =IPMT($C$4/12,1,$C$5,C18) -> #NUM! | F19: =PMT($C$4/12,$C$5,$C$3) -> #NUM! | L19: 3 | M19: =IF(N18>0.00001,Q19-R19,0)*-1 -> #DIV/0! | N19: =MAX(N18-O19,0) -> #DIV/0! | O19: =$N$16/$N$5 -> #DIV/0! | P19: =N18*$N$4/12 -> #DIV/0! | Q19: =P19+O19 -> #DIV/0!
A20: 4 | B20: =IF(C19>0.00001,F20-G20,0) -> #NUM! | C20: =MAX(C19-D20,0) -> #NUM! | D20: =(F20-E20)*-1 -> #NUM! | E20: =IPMT($C$4/12,1,$C$5,C19) -> #NUM! | F20: =PMT($C$4/12,$C$5,$C$3) -> #NUM! | L20: 4 | M20: =IF(N19>0.00001,Q20-R20,0)*-1 -> #DIV/0! | N20: =MAX(N19-O20,0) -> #DIV/0! | O20: =$N$16/$N$5 -> #DIV/0! | P20: =N19*$N$4/12 -> #DIV/0! | Q20: =P20+O20 -> #DIV/0!
A21: 5 | B21: =IF(C20>0.00001,F21-G21,0) -> #NUM! | C21: =MAX(C20-D21,0) -> #NUM! | D21: =(F21-E21)*-1 -> #NUM! | E21: =IPMT($C$4/12,1,$C$5,C20) -> #NUM! | F21: =PMT($C$4/12,$C$5,$C$3) -> #NUM! | L21: 5 | M21: =IF(N20>0.00001,Q21-R21,0)*-1 -> #DIV/0! | N21: =MAX(N20-O21,0) -> #DIV/0! | O21: =$N$16/$N$5 -> #DIV/0! | P21: =N20*$N$4/12 -> #DIV/0! | Q21: =P21+O21 -> #DIV/0!
A22: 6 | B22: =IF(C21>0.00001,F22-G22,0) -> #NUM! | C22: =MAX(C21-D22,0) -> #NUM! | D22: =(F22-E22)*-1 -> #NUM! | E22: =IPMT($C$4/12,1,$C$5,C21) -> #NUM! | F22: =PMT($C$4/12,$C$5,$C$3) -> #NUM! | L22: 6 | M22: =IF(N21>0.00001,Q22-R22,0)*-1 -> #DIV/0! | N22: =MAX(N21-O22,0) -> #DIV/0! | O22: =$N$16/$N$5 -> #DIV/0! | P22: =N21*$N$4/12 -> #DIV/0! | Q22: =P22+O22 -> #DIV/0!
A23: 7 | B23: =IF(C22>0.00001,F23-G23,0) -> #NUM! | C23: =MAX(C22-D23,0) -> #NUM! | D23: =(F23-E23)*-1 -> #NUM! | E23: =IPMT($C$4/12,1,$C$5,C22) -> #NUM! | F23: =PMT($C$4/12,$C$5,$C$3) -> #NUM! | L23: 7 | M23: =IF(N22>0.00001,Q23-R23,0)*-1 -> #DIV/0! | N23: =MAX(N22-O23,0) -> #DIV/0! | O23: =$N$16/$N$5 -> #DIV/0! | P23: =N22*$N$4/12 -> #DIV/0! | Q23: =P23+O23 -> #DIV/0!
A24: 8 | B24: =IF(C23>0.00001,F24-G24,0) -> #NUM! | C24: =MAX(C23-D24,0) -> #NUM! | D24: =(F24-E24)*-1 -> #NUM! | E24: =IPMT($C$4/12,1,$C$5,C23) -> #NUM! | F24: =PMT($C$4/12,$C$5,$C$3) -> #NUM! | L24: 8 | M24: =IF(N23>0.00001,Q24-R24,0)*-1 -> #DIV/0! | N24: =MAX(N23-O24,0) -> #DIV/0! | O24: =$N$16/$N$5 -> #DIV/0! | P24: =N23*$N$4/12 -> #DIV/0! | Q24: =P24+O24 -> #DIV/0!
A25: 9 | B25: =IF(C24>0.00001,F25-G25,0) -> #NUM! | C25: =MAX(C24-D25,0) -> #NUM! | D25: =(F25-E25)*-1 -> #NUM! | E25: =IPMT($C$4/12,1,$C$5,C24) -> #NUM! | F25: =PMT($C$4/12,$C$5,$C$3) -> #NUM! | L25: 9 | M25: =IF(N24>0.00001,Q25-R25,0)*-1 -> #DIV/0! | N25: =MAX(N24-O25,0) -> #DIV/0! | O25: =$N$16/$N$5 -> #DIV/0! | P25: =N24*$N$4/12 -> #DIV/0! | Q25: =P25+O25 -> #DIV/0!
A26: 10 | B26: =IF(C25>0.00001,F26-G26,0) -> #NUM! | C26: =MAX(C25-D26,0) -> #NUM! | D26: =(F26-E26)*-1 -> #NUM! | E26: =IPMT($C$4/12,1,$C$5,C25) -> #NUM! | F26: =PMT($C$4/12,$C$5,$C$3) -> #NUM! | L26: 10 | M26: =IF(N25>0.00001,Q26-R26,0)*-1 -> #DIV/0! | N26: =MAX(N25-O26,0) -> #DIV/0! | O26: =$N$16/$N$5 -> #DIV/0! | P26: =N25*$N$4/12 -> #DIV/0! | Q26: =P26+O26 -> #DIV/0!
A27: 11 | B27: =IF(C26>0.00001,F27-G27,0) -> #NUM! | C27: =MAX(C26-D27,0) -> #NUM! | D27: =(F27-E27)*-1 -> #NUM! | E27: =IPMT($C$4/12,1,$C$5,C26) -> #NUM! | F27: =PMT($C$4/12,$C$5,$C$3) -> #NUM! | L27: 11 | M27: =IF(N26>0.00001,Q27-R27,0)*-1 -> #DIV/0! | N27: =MAX(N26-O27,0) -> #DIV/0! | O27: =$N$16/$N$5 -> #DIV/0! | P27: =N26*$N$4/12 -> #DIV/0! | Q27: =P27+O27 -> #DIV/0!
A28: 12 | B28: =IF(C27>0.00001,F28-G28,0) -> #NUM! | C28: =MAX(C27-D28,0) -> #NUM! | D28: =(F28-E28)*-1 -> #NUM! | E28: =IPMT($C$4/12,1,$C$5,C27) -> #NUM! | F28: =PMT($C$4/12,$C$5,$C$3) -> #NUM! | L28: 12 | M28: =IF(N27>0.00001,Q28-R28,0)*-1 -> #DIV/0! | N28: =MAX(N27-O28,0) -> #DIV/0! | O28: =$N$16/$N$5 -> #DIV/0! | P28: =N27*$N$4/12 -> #DIV/0! | Q28: =P28+O28 -> #DIV/0!
A29: 13 | B29: =IF(C28>0.00001,F29-G29,0) -> #NUM! | C29: =MAX(C28-D29,0) -> #NUM! | D29: =(F29-E29)*-1 -> #NUM! | E29: =IPMT($C$4/12,1,$C$5,C28) -> #NUM! | F29: =PMT($C$4/12,$C$5,$C$3) -> #NUM! | L29: 13 | M29: =IF(N28>0.00001,Q29-R29,0)*-1 -> #DIV/0! | N29: =MAX(N28-O29,0) -> #DIV/0! | O29: =$N$16/$N$5 -> #DIV/0! | P29: =N28*$N$4/12 -> #DIV/0! | Q29: =P29+O29 -> #DIV/0!
... A40: 24 | B40: =IF(C39>0.00001,F40-G40,0) -> #NUM! | C40: =MAX(C39-D40,0) -> #NUM! | D40: =(F40-E40)*-1 -> #NUM! | E40: =IPMT($C$4/12,1,$C$5,C39) -> #NUM! | F40: =PMT($C$4/12,$C$5,$C$3) -> #NUM! | L40: 24 | M40: =IF(N39>0.00001,Q40-R40,0)*-1 -> #DIV/0! | N40: =MAX(N39-O40,0) -> #DIV/0! | O40: =$N$16/$N$5 -> #DIV/0! | P40: =N39*$N$4/12 -> #DIV/0! | Q40: =P40+O40 -> #DIV/0!
A41: 25 | B41: =IF(C40>0.00001,F41-G41,0) -> #NUM! | C41: =MAX(C40-D41,0) -> #NUM! | D41: =(F41-E41)*-1 -> #NUM! | E41: =IPMT($C$4/12,1,$C$5,C40) -> #NUM! | F41: =PMT($C$4/12,$C$5,$C$3) -> #NUM! | G41: =IF('prijem_zahranicie - viac-dom'!$I$121=TRUE,IF($C$11>0,0.00025*C40,0),IF('prijem_zahranicie - viac-dom'!$I$122=TRUE,IF('prijem_zahranicie - viac-dom'!$F$122>0,0.00025*C40,0),0)) -> 0 | L41: 25 | M41: =IF(N40>0.00001,Q41-R41,0)*-1 -> #DIV/0! | N41: =MAX(N40-O41,0) -> #DIV/0! | O41: =$N$16/$N$5 -> #DIV/0! | P41: =N40*$N$4/12 -> #DIV/0! | Q41: =P41+O41 -> #DIV/0! | R41: =IF('prijem_zahranicie - viac-dom'!$I$121=TRUE,IF($C$11>0,0.00025*N40,0),IF('prijem_zahranicie - viac-dom'!$I$122=TRUE,IF('prijem_zahranicie - viac-dom'!$F$122>0,0.00025*N40*-1,0),0)) -> 0
A42: 26 | B42: =IF(C41>0.00001,F42-G42,0) -> #NUM! | C42: =MAX(C41-D42,0) -> #NUM! | D42: =(F42-E42)*-1 -> #NUM! | E42: =IPMT($C$4/12,1,$C$5,C41) -> #NUM! | F42: =PMT($C$4/12,$C$5,$C$3) -> #NUM! | G42: =IF('prijem_zahranicie - viac-dom'!$I$121=TRUE,IF($C$11>0,0.00025*C41,0),IF('prijem_zahranicie - viac-dom'!$I$122=TRUE,IF('prijem_zahranicie - viac-dom'!$F$122>0,0.00025*C41,0),0)) -> 0 | L42: 26 | M42: =IF(N41>0.00001,Q42-R42,0)*-1 -> #DIV/0! | N42: =MAX(N41-O42,0) -> #DIV/0! | O42: =$N$16/$N$5 -> #DIV/0! | P42: =N41*$N$4/12 -> #DIV/0! | Q42: =P42+O42 -> #DIV/0! | R42: =IF('prijem_zahranicie - viac-dom'!$I$121=TRUE,IF($C$11>0,0.00025*N41,0),IF('prijem_zahranicie - viac-dom'!$I$122=TRUE,IF('prijem_zahranicie - viac-dom'!$F$122>0,0.00025*N41*-1,0),0)) -> 0
A43: 27 | B43: =IF(C42>0.00001,F43-G43,0) -> #NUM! | C43: =MAX(C42-D43,0) -> #NUM! | D43: =(F43-E43)*-1 -> #NUM! | E43: =IPMT($C$4/12,1,$C$5,C42) -> #NUM! | F43: =PMT($C$4/12,$C$5,$C$3) -> #NUM! | G43: =IF('prijem_zahranicie - viac-dom'!$I$121=TRUE,IF($C$11>0,0.00025*C42,0),IF('prijem_zahranicie - viac-dom'!$I$122=TRUE,IF('prijem_zahranicie - viac-dom'!$F$122>0,0.00025*C42,0),0)) -> 0 | L43: 27 | M43: =IF(N42>0.00001,Q43-R43,0)*-1 -> #DIV/0! | N43: =MAX(N42-O43,0) -> #DIV/0! | O43: =$N$16/$N$5 -> #DIV/0! | P43: =N42*$N$4/12 -> #DIV/0! | Q43: =P43+O43 -> #DIV/0! | R43: =IF('prijem_zahranicie - viac-dom'!$I$121=TRUE,IF($C$11>0,0.00025*N42,0),IF('prijem_zahranicie - viac-dom'!$I$122=TRUE,IF('prijem_zahranicie - viac-dom'!$F$122>0,0.00025*N42*-1,0),0)) -> 0
A44: 28 | B44: =IF(C43>0.00001,F44-G44,0) -> #NUM! | C44: =MAX(C43-D44,0) -> #NUM! | D44: =(F44-E44)*-1 -> #NUM! | E44: =IPMT($C$4/12,1,$C$5,C43) -> #NUM! | F44: =PMT($C$4/12,$C$5,$C$3) -> #NUM! | G44: =IF('prijem_zahranicie - viac-dom'!$I$121=TRUE,IF($C$11>0,0.00025*C43,0),IF('prijem_zahranicie - viac-dom'!$I$122=TRUE,IF('prijem_zahranicie - viac-dom'!$F$122>0,0.00025*C43,0),0)) -> 0 | L44: 28 | M44: =IF(N43>0.00001,Q44-R44,0)*-1 -> #DIV/0! | N44: =MAX(N43-O44,0) -> #DIV/0! | O44: =$N$16/$N$5 -> #DIV/0! | P44: =N43*$N$4/12 -> #DIV/0! | Q44: =P44+O44 -> #DIV/0! | R44: =IF('prijem_zahranicie - viac-dom'!$I$121=TRUE,IF($C$11>0,0.00025*N43,0),IF('prijem_zahranicie - viac-dom'!$I$122=TRUE,IF('prijem_zahranicie - viac-dom'!$F$122>0,0.00025*N43*-1,0),0)) -> 0
A45: 29 | B45: =IF(C44>0.00001,F45-G45,0) -> #NUM! | C45: =MAX(C44-D45,0) -> #NUM! | D45: =(F45-E45)*-1 -> #NUM! | E45: =IPMT($C$4/12,1,$C$5,C44) -> #NUM! | F45: =PMT($C$4/12,$C$5,$C$3) -> #NUM! | G45: =IF('prijem_zahranicie - viac-dom'!$I$121=TRUE,IF($C$11>0,0.00025*C44,0),IF('prijem_zahranicie - viac-dom'!$I$122=TRUE,IF('prijem_zahranicie - viac-dom'!$F$122>0,0.00025*C44,0),0)) -> 0 | L45: 29 | M45: =IF(N44>0.00001,Q45-R45,0)*-1 -> #DIV/0! | N45: =MAX(N44-O45,0) -> #DIV/0! | O45: =$N$16/$N$5 -> #DIV/0! | P45: =N44*$N$4/12 -> #DIV/0! | Q45: =P45+O45 -> #DIV/0! | R45: =IF('prijem_zahranicie - viac-dom'!$I$121=TRUE,IF($C$11>0,0.00025*N44,0),IF('prijem_zahranicie - viac-dom'!$I$122=TRUE,IF('prijem_zahranicie - viac-dom'!$F$122>0,0.00025*N44*-1,0),0)) -> 0
A46: 30 | B46: =IF(C45>0.00001,F46-G46,0) -> #NUM! | C46: =MAX(C45-D46,0) -> #NUM! | D46: =(F46-E46)*-1 -> #NUM! | E46: =IPMT($C$4/12,1,$C$5,C45) -> #NUM! | F46: =PMT($C$4/12,$C$5,$C$3) -> #NUM! | G46: =IF('prijem_zahranicie - viac-dom'!$I$121=TRUE,IF($C$11>0,0.00025*C45,0),IF('prijem_zahranicie - viac-dom'!$I$122=TRUE,IF('prijem_zahranicie - viac-dom'!$F$122>0,0.00025*C45,0),0)) -> 0 | L46: 30 | M46: =IF(N45>0.00001,Q46-R46,0)*-1 -> #DIV/0! | N46: =MAX(N45-O46,0) -> #DIV/0! | O46: =$N$16/$N$5 -> #DIV/0! | P46: =N45*$N$4/12 -> #DIV/0! | Q46: =P46+O46 -> #DIV/0! | R46: =IF('prijem_zahranicie - viac-dom'!$I$121=TRUE,IF($C$11>0,0.00025*N45,0),IF('prijem_zahranicie - viac-dom'!$I$122=TRUE,IF('prijem_zahranicie - viac-dom'!$F$122>0,0.00025*N45*-1,0),0)) -> 0
A47: 31 | B47: =IF(C46>0.00001,F47-G47,0) -> #NUM! | C47: =MAX(C46-D47,0) -> #NUM! | D47: =(F47-E47)*-1 -> #NUM! | E47: =IPMT($C$4/12,1,$C$5,C46) -> #NUM! | F47: =PMT($C$4/12,$C$5,$C$3) -> #NUM! | G47: =IF('prijem_zahranicie - viac-dom'!$I$121=TRUE,IF($C$11>0,0.00025*C46,0),IF('prijem_zahranicie - viac-dom'!$I$122=TRUE,IF('prijem_zahranicie - viac-dom'!$F$122>0,0.00025*C46,0),0)) -> 0 | L47: 31 | M47: =IF(N46>0.00001,Q47-R47,0)*-1 -> #DIV/0! | N47: =MAX(N46-O47,0) -> #DIV/0! | O47: =$N$16/$N$5 -> #DIV/0! | P47: =N46*$N$4/12 -> #DIV/0! | Q47: =P47+O47 -> #DIV/0! | R47: =IF('prijem_zahranicie - viac-dom'!$I$121=TRUE,IF($C$11>0,0.00025*N46,0),IF('prijem_zahranicie - viac-dom'!$I$122=TRUE,IF('prijem_zahranicie - viac-dom'!$F$122>0,0.00025*N46*-1,0),0)) -> 0
A48: 32 | B48: =IF(C47>0.00001,F48-G48,0) -> #NUM! | C48: =MAX(C47-D48,0) -> #NUM! | D48: =(F48-E48)*-1 -> #NUM! | E48: =IPMT($C$4/12,1,$C$5,C47) -> #NUM! | F48: =PMT($C$4/12,$C$5,$C$3) -> #NUM! | G48: =IF('prijem_zahranicie - viac-dom'!$I$121=TRUE,IF($C$11>0,0.00025*C47,0),IF('prijem_zahranicie - viac-dom'!$I$122=TRUE,IF('prijem_zahranicie - viac-dom'!$F$122>0,0.00025*C47,0),0)) -> 0 | L48: 32 | M48: =IF(N47>0.00001,Q48-R48,0)*-1 -> #DIV/0! | N48: =MAX(N47-O48,0) -> #DIV/0! | O48: =$N$16/$N$5 -> #DIV/0! | P48: =N47*$N$4/12 -> #DIV/0! | Q48: =P48+O48 -> #DIV/0! | R48: =IF('prijem_zahranicie - viac-dom'!$I$121=TRUE,IF($C$11>0,0.00025*N47,0),IF('prijem_zahranicie - viac-dom'!$I$122=TRUE,IF('prijem_zahranicie - viac-dom'!$F$122>0,0.00025*N47*-1,0),0)) -> 0
A49: 33 | B49: =IF(C48>0.00001,F49-G49,0) -> #NUM! | C49: =MAX(C48-D49,0) -> #NUM! | D49: =(F49-E49)*-1 -> #NUM! | E49: =IPMT($C$4/12,1,$C$5,C48) -> #NUM! | F49: =PMT($C$4/12,$C$5,$C$3) -> #NUM! | G49: =IF('prijem_zahranicie - viac-dom'!$I$121=TRUE,IF($C$11>0,0.00025*C48,0),IF('prijem_zahranicie - viac-dom'!$I$122=TRUE,IF('prijem_zahranicie - viac-dom'!$F$122>0,0.00025*C48,0),0)) -> 0 | L49: 33 | M49: =IF(N48>0.00001,Q49-R49,0)*-1 -> #DIV/0! | N49: =MAX(N48-O49,0) -> #DIV/0! | O49: =$N$16/$N$5 -> #DIV/0! | P49: =N48*$N$4/12 -> #DIV/0! | Q49: =P49+O49 -> #DIV/0! | R49: =IF('prijem_zahranicie - viac-dom'!$I$121=TRUE,IF($C$11>0,0.00025*N48,0),IF('prijem_zahranicie - viac-dom'!$I$122=TRUE,IF('prijem_zahranicie - viac-dom'!$F$122>0,0.00025*N48*-1,0),0)) -> 0
A50: 34 | B50: =IF(C49>0.00001,F50-G50,0) -> #NUM! | C50: =MAX(C49-D50,0) -> #NUM! | D50: =(F50-E50)*-1 -> #NUM! | E50: =IPMT($C$4/12,1,$C$5,C49) -> #NUM! | F50: =PMT($C$4/12,$C$5,$C$3) -> #NUM! | G50: =IF('prijem_zahranicie - viac-dom'!$I$121=TRUE,IF($C$11>0,0.00025*C49,0),IF('prijem_zahranicie - viac-dom'!$I$122=TRUE,IF('prijem_zahranicie - viac-dom'!$F$122>0,0.00025*C49,0),0)) -> 0 | L50: 34 | M50: =IF(N49>0.00001,Q50-R50,0)*-1 -> #DIV/0! | N50: =MAX(N49-O50,0) -> #DIV/0! | O50: =$N$16/$N$5 -> #DIV/0! | P50: =N49*$N$4/12 -> #DIV/0! | Q50: =P50+O50 -> #DIV/0! | R50: =IF('prijem_zahranicie - viac-dom'!$I$121=TRUE,IF($C$11>0,0.00025*N49,0),IF('prijem_zahranicie - viac-dom'!$I$122=TRUE,IF('prijem_zahranicie - viac-dom'!$F$122>0,0.00025*N49*-1,0),0)) -> 0
A51: 35 | B51: =IF(C50>0.00001,F51-G51,0) -> #NUM! | C51: =MAX(C50-D51,0) -> #NUM! | D51: =(F51-E51)*-1 -> #NUM! | E51: =IPMT($C$4/12,1,$C$5,C50) -> #NUM! | F51: =PMT($C$4/12,$C$5,$C$3) -> #NUM! | G51: =IF('prijem_zahranicie - viac-dom'!$I$121=TRUE,IF($C$11>0,0.00025*C50,0),IF('prijem_zahranicie - viac-dom'!$I$122=TRUE,IF('prijem_zahranicie - viac-dom'!$F$122>0,0.00025*C50,0),0)) -> 0 | L51: 35 | M51: =IF(N50>0.00001,Q51-R51,0)*-1 -> #DIV/0! | N51: =MAX(N50-O51,0) -> #DIV/0! | O51: =$N$16/$N$5 -> #DIV/0! | P51: =N50*$N$4/12 -> #DIV/0! | Q51: =P51+O51 -> #DIV/0! | R51: =IF('prijem_zahranicie - viac-dom'!$I$121=TRUE,IF($C$11>0,0.00025*N50,0),IF('prijem_zahranicie - viac-dom'!$I$122=TRUE,IF('prijem_zahranicie - viac-dom'!$F$122>0,0.00025*N50*-1,0),0)) -> 0
A52: 36 | B52: =IF(C51>0.00001,F52-G52,0) -> #NUM! | C52: =MAX(C51-D52,0) -> #NUM! | D52: =(F52-E52)*-1 -> #NUM! | E52: =IPMT($C$4/12,1,$C$5,C51) -> #NUM! | F52: =PMT($C$4/12,$C$5,$C$3) -> #NUM! | G52: =IF('prijem_zahranicie - viac-dom'!$I$121=TRUE,IF($C$11>0,0.00025*C51,0),IF('prijem_zahranicie - viac-dom'!$I$122=TRUE,IF('prijem_zahranicie - viac-dom'!$F$122>0,0.00025*C51,0),0)) -> 0 | L52: 36 | M52: =IF(N51>0.00001,Q52-R52,0)*-1 -> #DIV/0! | N52: =MAX(N51-O52,0) -> #DIV/0! | O52: =$N$16/$N$5 -> #DIV/0! | P52: =N51*$N$4/12 -> #DIV/0! | Q52: =P52+O52 -> #DIV/0! | R52: =IF('prijem_zahranicie - viac-dom'!$I$121=TRUE,IF($C$11>0,0.00025*N51,0),IF('prijem_zahranicie - viac-dom'!$I$122=TRUE,IF('prijem_zahranicie - viac-dom'!$F$122>0,0.00025*N51*-1,0),0)) -> 0
... A496: 480 | B496: =IF(C495>0.00001,F496-G496,0) -> #NUM! | C496: =MAX(C495-D496,0) -> #NUM! | D496: =(F496-E496)*-1 -> #NUM! | E496: =IPMT($C$4/12,1,$C$5,C495) -> #NUM! | F496: =PMT($C$4/12,$C$5,$C$3) -> #NUM! | G496: =IF('prijem_zahranicie - viac-dom'!$I$121=TRUE,IF($C$11>0,0.00025*C495,0),IF('prijem_zahranicie - viac-dom'!$I$122=TRUE,IF('prijem_zahranicie - viac-dom'!$F$122>0,0.00025*C495,0),0)) -> 0 | L496: 480 | M496: =IF(N495>0.00001,Q496-R496,0)*-1 -> #DIV/0! | N496: =MAX(N495-O496,0) -> #DIV/0! | O496: =$N$16/$N$5 -> #DIV/0! | P496: =N495*$N$4/12 -> #DIV/0! | Q496: =P496+O496 -> #DIV/0! | R496: =IF('prijem_zahranicie - viac-dom'!$I$121=TRUE,IF($C$11>0,0.00025*N495,0),IF('prijem_zahranicie - viac-dom'!$I$122=TRUE,IF('prijem_zahranicie - viac-dom'!$F$122>0,0.00025*N495*-1,0),0)) -> 0
A497: 481 | L497: 481

Sheet rovne_splatky
A1: Predbežný harmonogram splátok - rovné splátky
A3: Výška úveru | B3: =IF('prijem - EUR'!F49>0,'prijem - EUR'!F49,vyska_uveru_z) -> 0
A4: Úroková sadzba | B4: =IF(urokova_sadzba>0,urokova_sadzba,urokova_sadzba_z) -> 0
A5: Počet splátok | B5: =IF(doba_m>0,doba_m,doba_m_z) -> 0 | C5: =SUM(B4/12) -> 0 | D5: =PMT(C5,B5,-B3) -> #NUM!
A7: Predbežný harmonogram splátok bude po poskytnutí úveru nahradený harmonogramom splátok dostupným prostredníctvom internet bankingu klienta
A9: Číslo splátky | B9: Splátka istiny | C9: Splátka úroku | D9: Mesačná splátka | E9: Zostatok istiny | F9: Poistenie LI
B10: EUR | C10: EUR | D10: EUR | E10: EUR | F10: EUR
E11: =SUM(B3) -> 0
A12: 1 | B12: =PPMT(C$5,A12,B$5,-E$11) -> #NUM! | C12: =IPMT(C$5,A12,B$5,-E$11) -> #NUM! | D12: =SUM($D$5) -> #NUM! | E12: =PV(C$5,B$5-A12,-D$12) -> #NUM!
A13: 2 | B13: =PPMT(C$5,A13,B$5,-E$11) -> #NUM! | C13: =IPMT(C$5,A13,B$5,-E$11) -> #NUM! | D13: =SUM($D$5) -> #NUM! | E13: =PV(C$5,B$5-A13,-D$12) -> #NUM!
A14: 3 | B14: =PPMT(C$5,A14,B$5,-E$11) -> #NUM! | C14: =IPMT(C$5,A14,B$5,-E$11) -> #NUM! | D14: =SUM($D$5) -> #NUM! | E14: =PV(C$5,B$5-A14,-D$12) -> #NUM!
A15: 4 | B15: =PPMT(C$5,A15,B$5,-E$11) -> #NUM! | C15: =IPMT(C$5,A15,B$5,-E$11) -> #NUM! | D15: =SUM($D$5) -> #NUM! | E15: =PV(C$5,B$5-A15,-D$12) -> #NUM!
A16: 5 | B16: =PPMT(C$5,A16,B$5,-E$11) -> #NUM! | C16: =IPMT(C$5,A16,B$5,-E$11) -> #NUM! | D16: =SUM($D$5) -> #NUM! | E16: =PV(C$5,B$5-A16,-D$12) -> #NUM!
A17: 6 | B17: =PPMT(C$5,A17,B$5,-E$11) -> #NUM! | C17: =IPMT(C$5,A17,B$5,-E$11) -> #NUM! | D17: =SUM($D$5) -> #NUM! | E17: =PV(C$5,B$5-A17,-D$12) -> #NUM!
A18: 7 | B18: =PPMT(C$5,A18,B$5,-E$11) -> #NUM! | C18: =IPMT(C$5,A18,B$5,-E$11) -> #NUM! | D18: =SUM($D$5) -> #NUM! | E18: =PV(C$5,B$5-A18,-D$12) -> #NUM!
A19: 8 | B19: =PPMT(C$5,A19,B$5,-E$11) -> #NUM! | C19: =IPMT(C$5,A19,B$5,-E$11) -> #NUM! | D19: =SUM($D$5) -> #NUM! | E19: =PV(C$5,B$5-A19,-D$12) -> #NUM!
A20: 9 | B20: =PPMT(C$5,A20,B$5,-E$11) -> #NUM! | C20: =IPMT(C$5,A20,B$5,-E$11) -> #NUM! | D20: =SUM($D$5) -> #NUM! | E20: =PV(C$5,B$5-A20,-D$12) -> #NUM!
A21: 10 | B21: =PPMT(C$5,A21,B$5,-E$11) -> #NUM! | C21: =IPMT(C$5,A21,B$5,-E$11) -> #NUM! | D21: =SUM($D$5) -> #NUM! | E21: =PV(C$5,B$5-A21,-D$12) -> #NUM!
A22: 11 | B22: =PPMT(C$5,A22,B$5,-E$11) -> #NUM! | C22: =IPMT(C$5,A22,B$5,-E$11) -> #NUM! | D22: =SUM($D$5) -> #NUM! | E22: =PV(C$5,B$5-A22,-D$12) -> #NUM!
A23: 12 | B23: =PPMT(C$5,A23,B$5,-E$11) -> #NUM! | C23: =IPMT(C$5,A23,B$5,-E$11) -> #NUM! | D23: =SUM($D$5) -> #NUM! | E23: =PV(C$5,B$5-A23,-D$12) -> #NUM!
... A35: 24 | B35: =PPMT(C$5,A35,B$5,-E$11) -> #NUM! | C35: =IPMT(C$5,A35,B$5,-E$11) -> #NUM! | D35: =SUM($D$5) -> #NUM! | E35: =PV(C$5,B$5-A35,-D$12) -> #NUM!
A36: 25 | B36: =PPMT(C$5,A36,B$5,-E$11) -> #NUM! | C36: =IPMT(C$5,A36,B$5,-E$11) -> #NUM! | D36: =SUM($D$5) -> #NUM! | E36: =PV(C$5,B$5-A36,-D$12) -> #NUM! | F36: =E36*0.00025 -> #NUM!
A37: 26 | B37: =PPMT(C$5,A37,B$5,-E$11) -> #NUM! | C37: =IPMT(C$5,A37,B$5,-E$11) -> #NUM! | D37: =SUM($D$5) -> #NUM! | E37: =PV(C$5,B$5-A37,-D$12) -> #NUM! | F37: =E37*0.00025 -> #NUM!
A38: 27 | B38: =PPMT(C$5,A38,B$5,-E$11) -> #NUM! | C38: =IPMT(C$5,A38,B$5,-E$11) -> #NUM! | D38: =SUM($D$5) -> #NUM! | E38: =PV(C$5,B$5-A38,-D$12) -> #NUM! | F38: =E38*0.00025 -> #NUM!
A39: 28 | B39: =PPMT(C$5,A39,B$5,-E$11) -> #NUM! | C39: =IPMT(C$5,A39,B$5,-E$11) -> #NUM! | D39: =SUM($D$5) -> #NUM! | E39: =PV(C$5,B$5-A39,-D$12) -> #NUM! | F39: =E39*0.00025 -> #NUM!
A40: 29 | B40: =PPMT(C$5,A40,B$5,-E$11) -> #NUM! | C40: =IPMT(C$5,A40,B$5,-E$11) -> #NUM! | D40: =SUM($D$5) -> #NUM! | E40: =PV(C$5,B$5-A40,-D$12) -> #NUM! | F40: =E40*0.00025 -> #NUM!
A41: 30 | B41: =PPMT(C$5,A41,B$5,-E$11) -> #NUM! | C41: =IPMT(C$5,A41,B$5,-E$11) -> #NUM! | D41: =SUM($D$5) -> #NUM! | E41: =PV(C$5,B$5-A41,-D$12) -> #NUM! | F41: =E41*0.00025 -> #NUM!
A42: 31 | B42: =PPMT(C$5,A42,B$5,-E$11) -> #NUM! | C42: =IPMT(C$5,A42,B$5,-E$11) -> #NUM! | D42: =SUM($D$5) -> #NUM! | E42: =PV(C$5,B$5-A42,-D$12) -> #NUM! | F42: =E42*0.00025 -> #NUM!
A43: 32 | B43: =PPMT(C$5,A43,B$5,-E$11) -> #NUM! | C43: =IPMT(C$5,A43,B$5,-E$11) -> #NUM! | D43: =SUM($D$5) -> #NUM! | E43: =PV(C$5,B$5-A43,-D$12) -> #NUM! | F43: =E43*0.00025 -> #NUM!
A44: 33 | B44: =PPMT(C$5,A44,B$5,-E$11) -> #NUM! | C44: =IPMT(C$5,A44,B$5,-E$11) -> #NUM! | D44: =SUM($D$5) -> #NUM! | E44: =PV(C$5,B$5-A44,-D$12) -> #NUM! | F44: =E44*0.00025 -> #NUM!
A45: 34 | B45: =PPMT(C$5,A45,B$5,-E$11) -> #NUM! | C45: =IPMT(C$5,A45,B$5,-E$11) -> #NUM! | D45: =SUM($D$5) -> #NUM! | E45: =PV(C$5,B$5-A45,-D$12) -> #NUM! | F45: =E45*0.00025 -> #NUM!
A46: 35 | B46: =PPMT(C$5,A46,B$5,-E$11) -> #NUM! | C46: =IPMT(C$5,A46,B$5,-E$11) -> #NUM! | D46: =SUM($D$5) -> #NUM! | E46: =PV(C$5,B$5-A46,-D$12) -> #NUM! | F46: =E46*0.00025 -> #NUM!
A47: 36 | B47: =PPMT(C$5,A47,B$5,-E$11) -> #NUM! | C47: =IPMT(C$5,A47,B$5,-E$11) -> #NUM! | D47: =SUM($D$5) -> #NUM! | E47: =PV(C$5,B$5-A47,-D$12) -> #NUM! | F47: =E47*0.00025 -> #NUM!
... A551: 540 | B551: =PPMT(C$5,A551,B$5,-E$11) -> #NUM! | C551: =IPMT(C$5,A551,B$5,-E$11) -> #NUM! | D551: =SUM($D$5) -> #NUM! | E551: =PV(C$5,B$5-A551,-D$12) -> #NUM! | F551: =E551*0.00025 -> #NUM!

Sheet klesajuce_splatky
A1: Predbežný harmonogram splátok - klesajúce splátky
A3: Výška úveru | B3: =IF('prijem - EUR'!F49>0,'prijem - EUR'!F49,vyska_uveru_z) -> 0 | D3: =SUM(D12:D551) -> #DIV/0!
A4: Úroková sadzba | B4: =IF(urokova_sadzba>0,urokova_sadzba,urokova_sadzba_z) -> 0
A5: Počet splátok | B5: =IF(doba_m>0,doba_m,doba_m_z) -> 0
A7: Predbežný harmonogram splátok bude po poskytnutí úveru nahradený harmonogramom splátok dostupným prostredníctvom internet bankingu klienta
A9: Číslo splátky | B9: Splátka istiny | C9: Splátka úroku | D9: Mesačná splátka | E9: Zostatok istiny | F9: Poistenie LI
B10: EUR | C10: EUR | D10: EUR | E10: EUR | F10: EUR
E11: =SUM(B3) -> 0
A12: 1 | B12: =SUM($B$3/$B$5) -> #DIV/0! | C12: =SUM(E11*($B$4*(1/12))) -> 0 | D12: =SUM(B12+C12) -> #DIV/0! | E12: =SUM(E11-B12) -> #DIV/0!
A13: 2 | B13: =SUM($B$3/$B$5) -> #DIV/0! | C13: =SUM(E12*($B$4*(1/12))) -> #DIV/0! | D13: =SUM(B13+C13) -> #DIV/0! | E13: =SUM(E12-B13) -> #DIV/0!
A14: 3 | B14: =SUM($B$3/$B$5) -> #DIV/0! | C14: =SUM(E13*($B$4*(1/12))) -> #DIV/0! | D14: =SUM(B14+C14) -> #DIV/0! | E14: =SUM(E13-B14) -> #DIV/0!
A15: 4 | B15: =SUM($B$3/$B$5) -> #DIV/0! | C15: =SUM(E14*($B$4*(1/12))) -> #DIV/0! | D15: =SUM(B15+C15) -> #DIV/0! | E15: =SUM(E14-B15) -> #DIV/0!
A16: 5 | B16: =SUM($B$3/$B$5) -> #DIV/0! | C16: =SUM(E15*($B$4*(1/12))) -> #DIV/0! | D16: =SUM(B16+C16) -> #DIV/0! | E16: =SUM(E15-B16) -> #DIV/0!
A17: 6 | B17: =SUM($B$3/$B$5) -> #DIV/0! | C17: =SUM(E16*($B$4*(1/12))) -> #DIV/0! | D17: =SUM(B17+C17) -> #DIV/0! | E17: =SUM(E16-B17) -> #DIV/0!
A18: 7 | B18: =SUM($B$3/$B$5) -> #DIV/0! | C18: =SUM(E17*($B$4*(1/12))) -> #DIV/0! | D18: =SUM(B18+C18) -> #DIV/0! | E18: =SUM(E17-B18) -> #DIV/0!
A19: 8 | B19: =SUM($B$3/$B$5) -> #DIV/0! | C19: =SUM(E18*($B$4*(1/12))) -> #DIV/0! | D19: =SUM(B19+C19) -> #DIV/0! | E19: =SUM(E18-B19) -> #DIV/0!
A20: 9 | B20: =SUM($B$3/$B$5) -> #DIV/0! | C20: =SUM(E19*($B$4*(1/12))) -> #DIV/0! | D20: =SUM(B20+C20) -> #DIV/0! | E20: =SUM(E19-B20) -> #DIV/0!
A21: 10 | B21: =SUM($B$3/$B$5) -> #DIV/0! | C21: =SUM(E20*($B$4*(1/12))) -> #DIV/0! | D21: =SUM(B21+C21) -> #DIV/0! | E21: =SUM(E20-B21) -> #DIV/0!
A22: 11 | B22: =SUM($B$3/$B$5) -> #DIV/0! | C22: =SUM(E21*($B$4*(1/12))) -> #DIV/0! | D22: =SUM(B22+C22) -> #DIV/0! | E22: =SUM(E21-B22) -> #DIV/0!
A23: 12 | B23: =SUM($B$3/$B$5) -> #DIV/0! | C23: =SUM(E22*($B$4*(1/12))) -> #DIV/0! | D23: =SUM(B23+C23) -> #DIV/0! | E23: =SUM(E22-B23) -> #DIV/0!
... A35: 24 | B35: =SUM($B$3/$B$5) -> #DIV/0! | C35: =SUM(E34*($B$4*(1/12))) -> #DIV/0! | D35: =SUM(B35+C35) -> #DIV/0! | E35: =SUM(E34-B35) -> #DIV/0!
A36: 25 | B36: =SUM($B$3/$B$5) -> #DIV/0! | C36: =SUM(E35*($B$4*(1/12))) -> #DIV/0! | D36: =SUM(B36+C36) -> #DIV/0! | E36: =SUM(E35-B36) -> #DIV/0! | F36: =E36*0.00025 -> #DIV/0!
A37: 26 | B37: =SUM($B$3/$B$5) -> #DIV/0! | C37: =SUM(E36*($B$4*(1/12))) -> #DIV/0! | D37: =SUM(B37+C37) -> #DIV/0! | E37: =SUM(E36-B37) -> #DIV/0! | F37: =E37*0.00025 -> #DIV/0!
A38: 27 | B38: =SUM($B$3/$B$5) -> #DIV/0! | C38: =SUM(E37*($B$4*(1/12))) -> #DIV/0! | D38: =SUM(B38+C38) -> #DIV/0! | E38: =SUM(E37-B38) -> #DIV/0! | F38: =E38*0.00025 -> #DIV/0!
A39: 28 | B39: =SUM($B$3/$B$5) -> #DIV/0! | C39: =SUM(E38*($B$4*(1/12))) -> #DIV/0! | D39: =SUM(B39+C39) -> #DIV/0! | E39: =SUM(E38-B39) -> #DIV/0! | F39: =E39*0.00025 -> #DIV/0!
A40: 29 | B40: =SUM($B$3/$B$5) -> #DIV/0! | C40: =SUM(E39*($B$4*(1/12))) -> #DIV/0! | D40: =SUM(B40+C40) -> #DIV/0! | E40: =SUM(E39-B40) -> #DIV/0! | F40: =E40*0.00025 -> #DIV/0!
A41: 30 | B41: =SUM($B$3/$B$5) -> #DIV/0! | C41: =SUM(E40*($B$4*(1/12))) -> #DIV/0! | D41: =SUM(B41+C41) -> #DIV/0! | E41: =SUM(E40-B41) -> #DIV/0! | F41: =E41*0.00025 -> #DIV/0!
A42: 31 | B42: =SUM($B$3/$B$5) -> #DIV/0! | C42: =SUM(E41*($B$4*(1/12))) -> #DIV/0! | D42: =SUM(B42+C42) -> #DIV/0! | E42: =SUM(E41-B42) -> #DIV/0! | F42: =E42*0.00025 -> #DIV/0!
A43: 32 | B43: =SUM($B$3/$B$5) -> #DIV/0! | C43: =SUM(E42*($B$4*(1/12))) -> #DIV/0! | D43: =SUM(B43+C43) -> #DIV/0! | E43: =SUM(E42-B43) -> #DIV/0! | F43: =E43*0.00025 -> #DIV/0!
A44: 33 | B44: =SUM($B$3/$B$5) -> #DIV/0! | C44: =SUM(E43*($B$4*(1/12))) -> #DIV/0! | D44: =SUM(B44+C44) -> #DIV/0! | E44: =SUM(E43-B44) -> #DIV/0! | F44: =E44*0.00025 -> #DIV/0!
A45: 34 | B45: =SUM($B$3/$B$5) -> #DIV/0! | C45: =SUM(E44*($B$4*(1/12))) -> #DIV/0! | D45: =SUM(B45+C45) -> #DIV/0! | E45: =SUM(E44-B45) -> #DIV/0! | F45: =E45*0.00025 -> #DIV/0!
A46: 35 | B46: =SUM($B$3/$B$5) -> #DIV/0! | C46: =SUM(E45*($B$4*(1/12))) -> #DIV/0! | D46: =SUM(B46+C46) -> #DIV/0! | E46: =SUM(E45-B46) -> #DIV/0! | F46: =E46*0.00025 -> #DIV/0!
A47: 36 | B47: =SUM($B$3/$B$5) -> #DIV/0! | C47: =SUM(E46*($B$4*(1/12))) -> #DIV/0! | D47: =SUM(B47+C47) -> #DIV/0! | E47: =SUM(E46-B47) -> #DIV/0! | F47: =E47*0.00025 -> #DIV/0!
... A551: 540 | B551: =SUM($B$3/$B$5) -> #DIV/0! | C551: =SUM(E550*($B$4*(1/12))) -> #DIV/0! | D551: =SUM(B551+C551) -> #DIV/0! | E551: =SUM(E550-B551) -> #DIV/0! | F551: =E551*0.00025 -> #DIV/0!
